{
  "place_id": "FR::evreux",
  "keywords": {
    "fr": [
      "Cathédrale Notre-Dame d'Évreux",
      "Beffroi d'Évreux",
      "Église Saint-Taurin Évreux",
      "Musée d'Art Histoire et Archéologie Évreux",
      "Site archéologique Gisacum"
    ],
    "en": [
      "Évreux Cathedral Notre-Dame",
      "Évreux Belfry",
      "Saint-Taurin Church Évreux",
      "Museum of Art History and Archaeology Évreux",
      "Gisacum Archaeological Site"
    ],
    "es": [
      "Catedral Notre-Dame de Évreux",
      "Campanario de Évreux",
      "Iglesia Saint-Taurin Évreux",
      "Museo de Arte Historia y Arqueología Évreux",
      "Sitio Arqueológico Gisacum"
    ],
    "it": [
      "Cattedrale Notre-Dame di Évreux",
      "Beffroi d'Évreux",
      "Chiesa Saint-Taurin Évreux",
      "Museo di Arte Storia e Archeologia Évreux",
      "Sito Archeologico Gisacum"
    ],
    "pt": [
      "Catedral Notre-Dame de Évreux",
      "Campanário de Évreux",
      "Igreja Saint-Taurin Évreux",
      "Museu de Arte História e Arqueologia Évreux",
      "Sítio Arqueológico Gisacum"
    ]
  },
  "updated_at": "2026-04-18T16:52:48.558Z"
}