{
  "version": 1,
  "generated_at": "2026-06-19T18:27:07.859Z",
  "total_itineraries": 4588,
  "latest_global": [
    {
      "itin_id": "es-baleares-ibiza-formentera-plages-scooter",
      "slug": "es-baleares-ibiza-formentera-plages-scooter",
      "country": "ES",
      "title": "Ibiza et Formentera en scooter : calas et plages en 7 j",
      "days": 8,
      "created_at": "2026-06-16T12:00:00Z",
      "langs": [
        {}
      ]
    },
    {
      "itin_id": "mk-macedoine-du-nord-grande-boucle-10j",
      "slug": "mk-macedoine-du-nord-grande-boucle-10j",
      "country": "MK",
      "title": "Macédoine du Nord : boucle de 10 jours, lacs et monastères",
      "days": 11,
      "created_at": "2026-06-15T12:00:00Z",
      "langs": [
        {}
      ]
    },
    {
      "itin_id": "rw-rwanda-grande-boucle-13j",
      "slug": "rw-rwanda-grande-boucle-13j",
      "country": "RW",
      "title": "Rwanda : boucle de 13 jours entre gorilles, lacs et volcans",
      "days": 14,
      "created_at": "2026-06-15T12:00:00Z",
      "langs": [
        {}
      ]
    },
    {
      "itin_id": "uy-uruguay-grande-boucle-16j",
      "slug": "uy-uruguay-grande-boucle-16j",
      "country": "UY",
      "title": "Uruguay : grande boucle de 16 jours, côte et pampa",
      "days": 17,
      "created_at": "2026-06-15T12:00:00Z",
      "langs": [
        {}
      ]
    },
    {
      "itin_id": "in-gujarat-grand-tour-gujarat",
      "slug": "in-gujarat-grand-tour-gujarat",
      "country": "IN",
      "title": "Gujarat: Grand UNESCO Sites Tour in 15 Days",
      "days": 15,
      "created_at": "2026-06-12T18:45:00Z",
      "langs": [
        {}
      ]
    },
    {
      "itin_id": "pl-dolny-slask-wroclaw-zamki-sudety",
      "slug": "pl-dolny-slask-wroclaw-zamki-sudety",
      "country": "PL",
      "title": "Wrocław, castillos de Silesia y Sudetes en 12 días",
      "days": 12,
      "created_at": "2026-06-12T18:44:02.110Z",
      "langs": [
        {}
      ]
    },
    {
      "itin_id": "mx-noreste-monterrey-coahuila-desierto",
      "slug": "mx-noreste-monterrey-coahuila-desierto",
      "country": "MX",
      "title": "Nordeste do México: Monterrey, deserto e Mapimí, 12 dias",
      "days": 12,
      "created_at": "2026-06-12T18:44:02.037Z",
      "langs": [
        {}
      ]
    },
    {
      "itin_id": "lt-vilnius-riga-pays-baltes-13j",
      "slug": "lt-vilnius-riga-pays-baltes-13j",
      "country": "LT",
      "title": "The Baltics: From Vilnius to the Dunes and Riga in 14 Days",
      "days": 14,
      "created_at": "2026-06-12T18:44:01.992Z",
      "langs": [
        {}
      ]
    },
    {
      "itin_id": "in-east-coast-chennai-visakhapatnam",
      "slug": "in-east-coast-chennai-visakhapatnam",
      "country": "IN",
      "title": "Costa este de la India: Chennai a Visakhapatnam, 13 días",
      "days": 13,
      "created_at": "2026-06-12T18:44:01.859Z",
      "langs": [
        {}
      ]
    },
    {
      "itin_id": "in-est-centre-bhubaneswar-bhopal",
      "slug": "in-est-centre-bhubaneswar-bhopal",
      "country": "IN",
      "title": "Da costa à selva: Bhubaneswar-Bhopal em 16 dias",
      "days": 16,
      "created_at": "2026-06-12T18:44:01.857Z",
      "langs": [
        {}
      ]
    },
    {
      "itin_id": "in-deccan-boucle-sultans-rois",
      "slug": "in-deccan-boucle-sultans-rois",
      "country": "IN",
      "title": "Decão: sultões bahmani e templos kakatiya em 12 dias",
      "days": 12,
      "created_at": "2026-06-12T18:44:01.853Z",
      "langs": [
        {}
      ]
    },
    {
      "itin_id": "hu-alfold-puszta-termes-grande-plaine",
      "slug": "hu-alfold-puszta-termes-grande-plaine",
      "country": "HU",
      "title": "Alföld: puszta, termas e Grande Planície em 9 dias",
      "days": 9,
      "created_at": "2026-06-12T18:44:01.806Z",
      "langs": [
        {}
      ]
    },
    {
      "itin_id": "cz-bohemia-prague-roches-villes-thermales",
      "slug": "cz-bohemia-prague-roches-villes-thermales",
      "country": "CZ",
      "title": "Bohemia: Prague, sandstone cities & thermal spas in 14 days",
      "days": 14,
      "created_at": "2026-06-12T18:44:01.448Z",
      "langs": [
        {}
      ]
    },
    {
      "itin_id": "cz-jizni-cechy-cesky-krumlov-zamky-rybniky",
      "slug": "cz-jizni-cechy-cesky-krumlov-zamky-rybniky",
      "country": "CZ",
      "title": "South Bohemia: Český Krumlov, Castles & Ponds in 10 Days",
      "days": 10,
      "created_at": "2026-06-12T14:30:00.000Z",
      "langs": [
        {}
      ]
    },
    {
      "itin_id": "es-castilla-la-mancha-manche-don-quichotte-sierra-segura",
      "slug": "es-castilla-la-mancha-manche-don-quichotte-sierra-segura",
      "country": "ES",
      "title": "Castilla-La Mancha: Windmills and Sierra in 10 Days",
      "days": 10,
      "created_at": "2026-06-12T14:30:00.000Z",
      "langs": [
        {}
      ]
    }
  ],
  "latest_by_lang": {
    "fr": [
      {
        "itin_id": "es-baleares-ibiza-formentera-plages-scooter",
        "slug": "es-baleares-ibiza-formentera-plages-scooter",
        "country": "ES",
        "title": "Ibiza et Formentera en scooter : calas et plages en 7 j",
        "days": 8,
        "created_at": "2026-06-16T12:00:00Z"
      },
      {
        "itin_id": "mk-macedoine-du-nord-grande-boucle-10j",
        "slug": "mk-macedoine-du-nord-grande-boucle-10j",
        "country": "MK",
        "title": "Macédoine du Nord : boucle de 10 jours, lacs et monastères",
        "days": 11,
        "created_at": "2026-06-15T12:00:00Z"
      },
      {
        "itin_id": "rw-rwanda-grande-boucle-13j",
        "slug": "rw-rwanda-grande-boucle-13j",
        "country": "RW",
        "title": "Rwanda : boucle de 13 jours entre gorilles, lacs et volcans",
        "days": 14,
        "created_at": "2026-06-15T12:00:00Z"
      },
      {
        "itin_id": "uy-uruguay-grande-boucle-16j",
        "slug": "uy-uruguay-grande-boucle-16j",
        "country": "UY",
        "title": "Uruguay : grande boucle de 16 jours, côte et pampa",
        "days": 17,
        "created_at": "2026-06-15T12:00:00Z"
      },
      {
        "itin_id": "in-gujarat-grand-tour-gujarat",
        "slug": "in-gujarat-grand-tour-gujarat",
        "country": "IN",
        "title": "Gujarat : grand tour des sites UNESCO en 15 jours",
        "days": 15,
        "created_at": "2026-06-12T12:00:00Z"
      },
      {
        "itin_id": "in-deccan-boucle-sultans-rois",
        "slug": "in-deccan-boucle-sultans-rois",
        "country": "IN",
        "title": "Deccan : sultans bahmani et temples kakatiya en 12 jours",
        "days": 12,
        "created_at": "2026-06-12T12:00:00Z"
      },
      {
        "itin_id": "in-est-centre-bhubaneswar-bhopal",
        "slug": "in-est-centre-bhubaneswar-bhopal",
        "country": "IN",
        "title": "De la côte à la jungle : Bhubaneswar-Bhopal en 16 jours",
        "days": 16,
        "created_at": "2026-06-12T12:00:00Z"
      },
      {
        "itin_id": "in-east-coast-chennai-visakhapatnam",
        "slug": "in-east-coast-chennai-visakhapatnam",
        "country": "IN",
        "title": "Côte est de l'Inde : Chennai à Visakhapatnam, 13 jours",
        "days": 13,
        "created_at": "2026-06-12T12:00:00Z"
      },
      {
        "itin_id": "cz-bohemia-prague-roches-villes-thermales",
        "slug": "cz-bohemia-prague-roches-villes-thermales",
        "country": "CZ",
        "title": "Bohême : Prague, grès et thermales en 14 jours",
        "days": 14,
        "created_at": "2026-06-11T12:00:00Z"
      },
      {
        "itin_id": "cz-jizni-cechy-cesky-krumlov-zamky-rybniky",
        "slug": "cz-jizni-cechy-cesky-krumlov-zamky-rybniky",
        "country": "CZ",
        "title": "Bohême du Sud : Český Krumlov, châteaux et étangs en 10 jours",
        "days": 10,
        "created_at": "2026-06-11T12:00:00Z"
      },
      {
        "itin_id": "es-castilla-la-mancha-manche-don-quichotte-sierra-segura",
        "slug": "es-castilla-la-mancha-manche-don-quichotte-sierra-segura",
        "country": "ES",
        "title": "Castille-La Manche : moulins et sierra en 10 jours",
        "days": 10,
        "created_at": "2026-06-11T12:00:00Z"
      },
      {
        "itin_id": "hu-alfold-puszta-termes-grande-plaine",
        "slug": "hu-alfold-puszta-termes-grande-plaine",
        "country": "HU",
        "title": "Alföld : puszta, thermes et Grande Plaine en 9 jours",
        "days": 9,
        "created_at": "2026-06-11T12:00:00Z"
      },
      {
        "itin_id": "lt-vilnius-riga-pays-baltes-13j",
        "slug": "lt-vilnius-riga-pays-baltes-13j",
        "country": "LT",
        "title": "Pays Baltes : de Vilnius aux dunes et à Riga en 14 jours",
        "days": 14,
        "created_at": "2026-06-11T12:00:00Z"
      },
      {
        "itin_id": "mx-noreste-monterrey-coahuila-desierto",
        "slug": "mx-noreste-monterrey-coahuila-desierto",
        "country": "MX",
        "title": "Nord-est Mexique : Monterrey, désert et Mapimí, 12 jours",
        "days": 12,
        "created_at": "2026-06-11T12:00:00Z"
      },
      {
        "itin_id": "pl-dolny-slask-wroclaw-zamki-sudety",
        "slug": "pl-dolny-slask-wroclaw-zamki-sudety",
        "country": "PL",
        "title": "Wrocław, châteaux de Silésie et Sudètes en 12 jours",
        "days": 12,
        "created_at": "2026-06-11T12:00:00Z"
      }
    ],
    "en": [
      {
        "itin_id": "mk-macedoine-du-nord-grande-boucle-10j",
        "slug": "mk-macedoine-du-nord-grande-boucle-10j",
        "country": "MK",
        "title": "Macédoine du Nord : boucle de 10 jours, lacs et monastères",
        "days": 11,
        "created_at": "2026-06-15T12:00:00Z"
      },
      {
        "itin_id": "rw-rwanda-grande-boucle-13j",
        "slug": "rw-rwanda-grande-boucle-13j",
        "country": "RW",
        "title": "Rwanda : boucle de 13 jours entre gorilles, lacs et volcans",
        "days": 14,
        "created_at": "2026-06-15T12:00:00Z"
      },
      {
        "itin_id": "uy-uruguay-grande-boucle-16j",
        "slug": "uy-uruguay-grande-boucle-16j",
        "country": "UY",
        "title": "Uruguay : grande boucle de 16 jours, côte et pampa",
        "days": 17,
        "created_at": "2026-06-15T12:00:00Z"
      },
      {
        "itin_id": "in-gujarat-grand-tour-gujarat",
        "slug": "in-gujarat-grand-tour-gujarat",
        "country": "IN",
        "title": "Gujarat: Grand UNESCO Sites Tour in 15 Days",
        "days": 15,
        "created_at": "2026-06-12T18:45:00Z"
      },
      {
        "itin_id": "pl-dolny-slask-wroclaw-zamki-sudety",
        "slug": "pl-dolny-slask-wroclaw-zamki-sudety",
        "country": "PL",
        "title": "Wrocław, Silesian Castles and the Sudetes in 12 Days",
        "days": 12,
        "created_at": "2026-06-12T18:44:02.109Z"
      },
      {
        "itin_id": "lt-vilnius-riga-pays-baltes-13j",
        "slug": "lt-vilnius-riga-pays-baltes-13j",
        "country": "LT",
        "title": "The Baltics: From Vilnius to the Dunes and Riga in 14 Days",
        "days": 14,
        "created_at": "2026-06-12T18:44:01.992Z"
      },
      {
        "itin_id": "in-east-coast-chennai-visakhapatnam",
        "slug": "in-east-coast-chennai-visakhapatnam",
        "country": "IN",
        "title": "India's East Coast: Chennai to Visakhapatnam, 13 Days",
        "days": 13,
        "created_at": "2026-06-12T18:44:01.858Z"
      },
      {
        "itin_id": "hu-alfold-puszta-termes-grande-plaine",
        "slug": "hu-alfold-puszta-termes-grande-plaine",
        "country": "HU",
        "title": "Alföld: Puszta, Thermal Baths, and the Great Plain in 9 Days",
        "days": 9,
        "created_at": "2026-06-12T18:44:01.803Z"
      },
      {
        "itin_id": "cz-bohemia-prague-roches-villes-thermales",
        "slug": "cz-bohemia-prague-roches-villes-thermales",
        "country": "CZ",
        "title": "Bohemia: Prague, sandstone cities & thermal spas in 14 days",
        "days": 14,
        "created_at": "2026-06-12T18:44:01.448Z"
      },
      {
        "itin_id": "mx-noreste-monterrey-coahuila-desierto",
        "slug": "mx-noreste-monterrey-coahuila-desierto",
        "country": "MX",
        "title": "Northeast Mexico: Monterrey, Desert & Mapimí, 12 Days",
        "days": 12,
        "created_at": "2026-06-12T18:30:00Z"
      },
      {
        "itin_id": "cz-jizni-cechy-cesky-krumlov-zamky-rybniky",
        "slug": "cz-jizni-cechy-cesky-krumlov-zamky-rybniky",
        "country": "CZ",
        "title": "South Bohemia: Český Krumlov, Castles & Ponds in 10 Days",
        "days": 10,
        "created_at": "2026-06-12T14:30:00.000Z"
      },
      {
        "itin_id": "es-castilla-la-mancha-manche-don-quichotte-sierra-segura",
        "slug": "es-castilla-la-mancha-manche-don-quichotte-sierra-segura",
        "country": "ES",
        "title": "Castilla-La Mancha: Windmills and Sierra in 10 Days",
        "days": 10,
        "created_at": "2026-06-12T14:30:00.000Z"
      },
      {
        "itin_id": "in-deccan-boucle-sultans-rois",
        "slug": "in-deccan-boucle-sultans-rois",
        "country": "IN",
        "title": "Deccan Trail: Bahmani Sultans and Kakatiya Temples in 12 Days",
        "days": 12,
        "created_at": "2026-06-12T14:30:00.000Z"
      },
      {
        "itin_id": "de-schleswig-holstein-frise-bruyere",
        "slug": "de-schleswig-holstein-frise-bruyere",
        "country": "DE",
        "title": "Schleswig-Holstein: Heathland, North Frisia and Sylt",
        "days": 15,
        "created_at": "2026-06-11T05:14:29.628Z"
      },
      {
        "itin_id": "de-westfalen-weser-muenster-kassel",
        "slug": "de-westfalen-weser-muenster-kassel",
        "country": "DE",
        "title": "Westphalia and the Weser Valley — Münster to Kassel in 9 Days",
        "days": 9,
        "created_at": "2026-06-11T05:14:29.626Z"
      }
    ],
    "es": [
      {
        "itin_id": "mk-macedoine-du-nord-grande-boucle-10j",
        "slug": "mk-macedoine-du-nord-grande-boucle-10j",
        "country": "MK",
        "title": "Macédoine du Nord : boucle de 10 jours, lacs et monastères",
        "days": 11,
        "created_at": "2026-06-15T12:00:00Z"
      },
      {
        "itin_id": "rw-rwanda-grande-boucle-13j",
        "slug": "rw-rwanda-grande-boucle-13j",
        "country": "RW",
        "title": "Rwanda : boucle de 13 jours entre gorilles, lacs et volcans",
        "days": 14,
        "created_at": "2026-06-15T12:00:00Z"
      },
      {
        "itin_id": "uy-uruguay-grande-boucle-16j",
        "slug": "uy-uruguay-grande-boucle-16j",
        "country": "UY",
        "title": "Uruguay : grande boucle de 16 jours, côte et pampa",
        "days": 17,
        "created_at": "2026-06-15T12:00:00Z"
      },
      {
        "itin_id": "pl-dolny-slask-wroclaw-zamki-sudety",
        "slug": "pl-dolny-slask-wroclaw-zamki-sudety",
        "country": "PL",
        "title": "Wrocław, castillos de Silesia y Sudetes en 12 días",
        "days": 12,
        "created_at": "2026-06-12T18:44:02.110Z"
      },
      {
        "itin_id": "in-east-coast-chennai-visakhapatnam",
        "slug": "in-east-coast-chennai-visakhapatnam",
        "country": "IN",
        "title": "Costa este de la India: Chennai a Visakhapatnam, 13 días",
        "days": 13,
        "created_at": "2026-06-12T18:44:01.859Z"
      },
      {
        "itin_id": "in-deccan-boucle-sultans-rois",
        "slug": "in-deccan-boucle-sultans-rois",
        "country": "IN",
        "title": "Decán: sultanatos bahmani y templos kakatiya en 12 días",
        "days": 12,
        "created_at": "2026-06-12T18:44:01.851Z"
      },
      {
        "itin_id": "in-gujarat-grand-tour-gujarat",
        "slug": "in-gujarat-grand-tour-gujarat",
        "country": "IN",
        "title": "Guyarat: gran ruta de sitios UNESCO en 15 días",
        "days": 15,
        "created_at": "2026-06-12T18:44:01.847Z"
      },
      {
        "itin_id": "hu-alfold-puszta-termes-grande-plaine",
        "slug": "hu-alfold-puszta-termes-grande-plaine",
        "country": "HU",
        "title": "Alföld: puszta, termas y Gran Llanura en 9 días",
        "days": 9,
        "created_at": "2026-06-12T18:30:00.000Z"
      },
      {
        "itin_id": "in-est-centre-bhubaneswar-bhopal",
        "slug": "in-est-centre-bhubaneswar-bhopal",
        "country": "IN",
        "title": "De la costa a la jungla: Bhubaneswar-Bhopal en 16 días",
        "days": 16,
        "created_at": "2026-06-12T18:30:00Z"
      },
      {
        "itin_id": "mx-noreste-monterrey-coahuila-desierto",
        "slug": "mx-noreste-monterrey-coahuila-desierto",
        "country": "MX",
        "title": "Noreste de México: Monterrey, desierto y Mapimí, 12 días",
        "days": 12,
        "created_at": "2026-06-12T18:30:00.000Z"
      },
      {
        "itin_id": "cz-jizni-cechy-cesky-krumlov-zamky-rybniky",
        "slug": "cz-jizni-cechy-cesky-krumlov-zamky-rybniky",
        "country": "CZ",
        "title": "Bohemia del Sur: Český Krumlov, castillos y estanques en 10 días",
        "days": 10,
        "created_at": "2026-06-12T14:30:00.000Z"
      },
      {
        "itin_id": "cz-bohemia-prague-roches-villes-thermales",
        "slug": "cz-bohemia-prague-roches-villes-thermales",
        "country": "CZ",
        "title": "Bohemia: Praga, areniscas y termas en 14 días",
        "days": 14,
        "created_at": "2026-06-12T14:30:00.000Z"
      },
      {
        "itin_id": "es-castilla-la-mancha-manche-don-quichotte-sierra-segura",
        "slug": "es-castilla-la-mancha-manche-don-quichotte-sierra-segura",
        "country": "ES",
        "title": "Castilla-La Mancha: molinos y sierra en 10 días",
        "days": 10,
        "created_at": "2026-06-12T14:30:00Z"
      },
      {
        "itin_id": "lt-vilnius-riga-pays-baltes-13j",
        "slug": "lt-vilnius-riga-pays-baltes-13j",
        "country": "LT",
        "title": "Países Bálticos: de Vilnius a las dunas y Riga en 14 días",
        "days": 14,
        "created_at": "2026-06-12T14:30:00.000Z"
      },
      {
        "itin_id": "tr-mer-noire-ouest-istanbul-safranbolu-bolu",
        "slug": "tr-mer-noire-ouest-istanbul-safranbolu-bolu",
        "country": "TR",
        "title": "Mar Negro y Safranbolu: 10 días de pueblo en pueblo",
        "days": 10,
        "created_at": "2026-06-11T05:14:30.322Z"
      }
    ],
    "pt": [
      {
        "itin_id": "mk-macedoine-du-nord-grande-boucle-10j",
        "slug": "mk-macedoine-du-nord-grande-boucle-10j",
        "country": "MK",
        "title": "Macédoine du Nord : boucle de 10 jours, lacs et monastères",
        "days": 11,
        "created_at": "2026-06-15T12:00:00Z"
      },
      {
        "itin_id": "rw-rwanda-grande-boucle-13j",
        "slug": "rw-rwanda-grande-boucle-13j",
        "country": "RW",
        "title": "Rwanda : boucle de 13 jours entre gorilles, lacs et volcans",
        "days": 14,
        "created_at": "2026-06-15T12:00:00Z"
      },
      {
        "itin_id": "uy-uruguay-grande-boucle-16j",
        "slug": "uy-uruguay-grande-boucle-16j",
        "country": "UY",
        "title": "Uruguay : grande boucle de 16 jours, côte et pampa",
        "days": 17,
        "created_at": "2026-06-15T12:00:00Z"
      },
      {
        "itin_id": "mx-noreste-monterrey-coahuila-desierto",
        "slug": "mx-noreste-monterrey-coahuila-desierto",
        "country": "MX",
        "title": "Nordeste do México: Monterrey, deserto e Mapimí, 12 dias",
        "days": 12,
        "created_at": "2026-06-12T18:44:02.037Z"
      },
      {
        "itin_id": "in-est-centre-bhubaneswar-bhopal",
        "slug": "in-est-centre-bhubaneswar-bhopal",
        "country": "IN",
        "title": "Da costa à selva: Bhubaneswar-Bhopal em 16 dias",
        "days": 16,
        "created_at": "2026-06-12T18:44:01.857Z"
      },
      {
        "itin_id": "in-deccan-boucle-sultans-rois",
        "slug": "in-deccan-boucle-sultans-rois",
        "country": "IN",
        "title": "Decão: sultões bahmani e templos kakatiya em 12 dias",
        "days": 12,
        "created_at": "2026-06-12T18:44:01.853Z"
      },
      {
        "itin_id": "hu-alfold-puszta-termes-grande-plaine",
        "slug": "hu-alfold-puszta-termes-grande-plaine",
        "country": "HU",
        "title": "Alföld: puszta, termas e Grande Planície em 9 dias",
        "days": 9,
        "created_at": "2026-06-12T18:44:01.806Z"
      },
      {
        "itin_id": "cz-bohemia-prague-roches-villes-thermales",
        "slug": "cz-bohemia-prague-roches-villes-thermales",
        "country": "CZ",
        "title": "Boémia: Praga, arenito e termas em 14 dias",
        "days": 14,
        "created_at": "2026-06-12T18:30:00.000Z"
      },
      {
        "itin_id": "in-east-coast-chennai-visakhapatnam",
        "slug": "in-east-coast-chennai-visakhapatnam",
        "country": "IN",
        "title": "Costa Leste da Índia: Chennai a Visakhapatnam, 13 dias",
        "days": 13,
        "created_at": "2026-06-12T18:30:00Z"
      },
      {
        "itin_id": "in-gujarat-grand-tour-gujarat",
        "slug": "in-gujarat-grand-tour-gujarat",
        "country": "IN",
        "title": "Gujarat: grande rota pelos sítios UNESCO em 15 dias",
        "days": 15,
        "created_at": "2026-06-12T18:30:00.000Z"
      },
      {
        "itin_id": "lt-vilnius-riga-pays-baltes-13j",
        "slug": "lt-vilnius-riga-pays-baltes-13j",
        "country": "LT",
        "title": "Países Bálticos: de Vilnius às dunas e Riga em 14 dias",
        "days": 14,
        "created_at": "2026-06-12T18:30:00.000Z"
      },
      {
        "itin_id": "pl-dolny-slask-wroclaw-zamki-sudety",
        "slug": "pl-dolny-slask-wroclaw-zamki-sudety",
        "country": "PL",
        "title": "Wrocław, castelos da Silésia e montes Sudetas em 12 dias",
        "days": 12,
        "created_at": "2026-06-12T18:30:00.000Z"
      },
      {
        "itin_id": "cz-jizni-cechy-cesky-krumlov-zamky-rybniky",
        "slug": "cz-jizni-cechy-cesky-krumlov-zamky-rybniky",
        "country": "CZ",
        "title": "Boémia do Sul: Český Krumlov, castelos e lagos em 10 dias",
        "days": 10,
        "created_at": "2026-06-12T14:30:00.000Z"
      },
      {
        "itin_id": "tr-anatolie-centrale-vallee-phrygienne-konya",
        "slug": "tr-anatolie-centrale-vallee-phrygienne-konya",
        "country": "TR",
        "title": "Anatólia Central: Frígia, Konya e caravançarais",
        "days": 13,
        "created_at": "2026-06-11T05:14:30.325Z"
      },
      {
        "itin_id": "sk-ouest-centre-chateaux-mines",
        "slug": "sk-ouest-centre-chateaux-mines",
        "country": "SK",
        "title": "Eslováquia: castelos, aldeias de madeira e minas em 11 dias",
        "days": 11,
        "created_at": "2026-06-11T05:14:30.291Z"
      }
    ],
    "it": [
      {
        "itin_id": "mk-macedoine-du-nord-grande-boucle-10j",
        "slug": "mk-macedoine-du-nord-grande-boucle-10j",
        "country": "MK",
        "title": "Macédoine du Nord : boucle de 10 jours, lacs et monastères",
        "days": 11,
        "created_at": "2026-06-15T12:00:00Z"
      },
      {
        "itin_id": "rw-rwanda-grande-boucle-13j",
        "slug": "rw-rwanda-grande-boucle-13j",
        "country": "RW",
        "title": "Rwanda : boucle de 13 jours entre gorilles, lacs et volcans",
        "days": 14,
        "created_at": "2026-06-15T12:00:00Z"
      },
      {
        "itin_id": "uy-uruguay-grande-boucle-16j",
        "slug": "uy-uruguay-grande-boucle-16j",
        "country": "UY",
        "title": "Uruguay : grande boucle de 16 jours, côte et pampa",
        "days": 17,
        "created_at": "2026-06-15T12:00:00Z"
      },
      {
        "itin_id": "mx-noreste-monterrey-coahuila-desierto",
        "slug": "mx-noreste-monterrey-coahuila-desierto",
        "country": "MX",
        "title": "Messico nord-orientale: Monterrey, deserto e Mapimí, 12 giorni",
        "days": 12,
        "created_at": "2026-06-12T18:44:02.037Z"
      },
      {
        "itin_id": "in-gujarat-grand-tour-gujarat",
        "slug": "in-gujarat-grand-tour-gujarat",
        "country": "IN",
        "title": "Gujarat: il gran tour dei siti UNESCO in 15 giorni",
        "days": 15,
        "created_at": "2026-06-12T18:44:01.848Z"
      },
      {
        "itin_id": "cz-bohemia-prague-roches-villes-thermales",
        "slug": "cz-bohemia-prague-roches-villes-thermales",
        "country": "CZ",
        "title": "Boemia: Praga, torri di arenaria e terme in 14 giorni",
        "days": 14,
        "created_at": "2026-06-12T18:30:00.000Z"
      },
      {
        "itin_id": "in-deccan-boucle-sultans-rois",
        "slug": "in-deccan-boucle-sultans-rois",
        "country": "IN",
        "title": "Deccan: sultanati bahmani e templi kakatiya in 12 giorni",
        "days": 12,
        "created_at": "2026-06-12T18:30:00.000Z"
      },
      {
        "itin_id": "cz-jizni-cechy-cesky-krumlov-zamky-rybniky",
        "slug": "cz-jizni-cechy-cesky-krumlov-zamky-rybniky",
        "country": "CZ",
        "title": "Boemia meridionale: Český Krumlov, castelli e stagni in 10 giorni",
        "days": 10,
        "created_at": "2026-06-12T14:30:00.000Z"
      },
      {
        "itin_id": "hu-alfold-puszta-termes-grande-plaine",
        "slug": "hu-alfold-puszta-termes-grande-plaine",
        "country": "HU",
        "title": "Alföld: puszta, terme e Grande Pianura in 9 giorni",
        "days": 9,
        "created_at": "2026-06-12T14:30:00.000Z"
      },
      {
        "itin_id": "in-est-centre-bhubaneswar-bhopal",
        "slug": "in-est-centre-bhubaneswar-bhopal",
        "country": "IN",
        "title": "Dalla costa alla giungla: Bhubaneswar-Bhopal in 16 giorni",
        "days": 16,
        "created_at": "2026-06-12T14:30:00.000Z"
      },
      {
        "itin_id": "lt-vilnius-riga-pays-baltes-13j",
        "slug": "lt-vilnius-riga-pays-baltes-13j",
        "country": "LT",
        "title": "Paesi Baltici: da Vilnius alle dune e a Riga in 14 giorni",
        "days": 14,
        "created_at": "2026-06-12T14:30:00.000Z"
      },
      {
        "itin_id": "pl-dolny-slask-wroclaw-zamki-sudety",
        "slug": "pl-dolny-slask-wroclaw-zamki-sudety",
        "country": "PL",
        "title": "Wrocław, castelli della Slesia e Sudeti in 12 giorni",
        "days": 12,
        "created_at": "2026-06-12T14:30:00Z"
      },
      {
        "itin_id": "tr-mer-noire-ouest-istanbul-safranbolu-bolu",
        "slug": "tr-mer-noire-ouest-istanbul-safranbolu-bolu",
        "country": "TR",
        "title": "Mar Nero & Safranbolu: 10 giorni di villaggio in villaggio",
        "days": 10,
        "created_at": "2026-06-11T05:14:30.079Z"
      },
      {
        "itin_id": "tr-transfrontalier-interieur-istanbul-sofia-rila",
        "slug": "tr-transfrontalier-interieur-istanbul-sofia-rila",
        "country": "TR",
        "title": "Da Istanbul a Sofia: Edirne, Plovdiv, Rila e i Rodopi",
        "days": 10,
        "created_at": "2026-06-08T14:32:00.000Z"
      },
      {
        "itin_id": "cz-stredocesky-sud-de-prague",
        "slug": "cz-stredocesky-sud-de-prague",
        "country": "CZ",
        "title": "7 giorni intorno a Praga: Kutná Hora, castelli e carso",
        "days": 7,
        "created_at": "2026-06-08T14:30:00Z"
      }
    ],
    "ar": [
      {
        "itin_id": "mk-macedoine-du-nord-grande-boucle-10j",
        "slug": "mk-macedoine-du-nord-grande-boucle-10j",
        "country": "MK",
        "title": "Macédoine du Nord : boucle de 10 jours, lacs et monastères",
        "days": 11,
        "created_at": "2026-06-15T12:00:00Z"
      },
      {
        "itin_id": "rw-rwanda-grande-boucle-13j",
        "slug": "rw-rwanda-grande-boucle-13j",
        "country": "RW",
        "title": "Rwanda : boucle de 13 jours entre gorilles, lacs et volcans",
        "days": 14,
        "created_at": "2026-06-15T12:00:00Z"
      },
      {
        "itin_id": "uy-uruguay-grande-boucle-16j",
        "slug": "uy-uruguay-grande-boucle-16j",
        "country": "UY",
        "title": "Uruguay : grande boucle de 16 jours, côte et pampa",
        "days": 17,
        "created_at": "2026-06-15T12:00:00Z"
      },
      {
        "itin_id": "ge-kakheti-georgia-wine-tbilisi-kakheti-7j",
        "slug": "ge-kakheti-georgia-wine-tbilisi-kakheti-7j",
        "country": "GE",
        "title": "Georgia: 7 Days at the Birthplace of Wine - Tbilisi, Kakheti and the Qvevri Route",
        "days": 7,
        "created_at": "2026-05-06T12:00:00Z"
      },
      {
        "itin_id": "ge-kakheti-georgia-wine-7-days",
        "slug": "ge-kakheti-georgia-wine-7-days",
        "country": "GE",
        "title": "Georgia: 8,000 Years of Wine in 7 Days",
        "days": 7,
        "created_at": "2026-05-06T12:00:00Z"
      },
      {
        "itin_id": "wf-islands-wallis-futuna-lagoons-and-marae",
        "slug": "wf-islands-wallis-futuna-lagoons-and-marae",
        "country": "WF",
        "title": "Wallis and Futuna: Lagoons, Crater Lakes and Tongan Marae",
        "days": 8,
        "created_at": "2026-04-23T16:42:34.246Z"
      },
      {
        "itin_id": "re-island-reunion-cirques-and-lava",
        "slug": "re-island-reunion-cirques-and-lava",
        "country": "RE",
        "title": "Réunion Island Circuit: Cirques, Volcanoes & Beaches",
        "days": 7.5,
        "created_at": "2026-04-20T18:30:00.000Z"
      },
      {
        "itin_id": "be-hai-mons-tournai-binche-lessines",
        "slug": "be-hai-mons-tournai-binche-lessines",
        "country": "BE",
        "title": "هينو الحضرية - مونس، تورناي، بينش وليسين",
        "days": 4,
        "created_at": "2026-03-05T12:00:00.000Z"
      },
      {
        "itin_id": "be-lux-han-laroche-bastogne-bouillon-semois",
        "slug": "be-lux-han-laroche-bastogne-bouillon-semois",
        "country": "BE",
        "title": "آردين العميقة - كهوف، حرب ونهر سيموا",
        "days": 5,
        "created_at": "2026-03-05T12:00:00.000Z"
      },
      {
        "itin_id": "at-autriche-two-weeks-explorers",
        "slug": "at-autriche-two-weeks-explorers",
        "country": "AT",
        "title": "النمسا في أسبوعين: فاخاو والألب وسالزبورغ",
        "days": 12,
        "created_at": "2026-03-04T12:52:04.262Z"
      },
      {
        "itin_id": "am-am-armenie-15-jours-yerevan-tatev-sevan-dilijan-debed",
        "slug": "am-am-armenie-15-jours-yerevan-tatev-sevan-dilijan-debed",
        "country": "AM",
        "title": "أرمينيا في 15 يومًا: يريفان، تاتيف، سيفان، ديليجان وأخدود ديبيد",
        "days": 15,
        "created_at": "2026-03-04T00:00:00.000Z"
      },
      {
        "itin_id": "ar-ar-cuyo-argentine-pays-du-vin-sommets-andins-et-paysages-d-un-autre-monde",
        "slug": "ar-ar-cuyo-argentine-pays-du-vin-sommets-andins-et-paysages-d-un-autre-monde",
        "country": "AR",
        "title": "رحلة كويو الأرجنتين: ميندوزا وكروم العنب وقمم جبال الأنديز",
        "days": 16,
        "created_at": "2026-03-04T00:00:00.000Z"
      },
      {
        "itin_id": "ar-country-grand-tour-argentina-23j",
        "slug": "ar-country-grand-tour-argentina-23j",
        "country": "AR",
        "title": "رحلة الأرجنتين الكبرى: من جبال الأنديز الشمالية إلى نهاية العالم",
        "days": 23,
        "created_at": "2026-03-04T00:00:00.000Z"
      },
      {
        "itin_id": "al-albanie-paysages-et-villes-incontournables",
        "slug": "al-albanie-paysages-et-villes-incontournables",
        "country": "AL",
        "title": "رحلة برية في ألبانيا: البحر والجبال ومسار متكامل",
        "days": 16,
        "created_at": "2026-03-02T00:00:00.000Z"
      },
      {
        "itin_id": "au-national-destinations-phares-2025",
        "slug": "au-national-destinations-phares-2025",
        "country": "AU",
        "title": "الجولة الكبرى في أستراليا: المواقع الطبيعية والتراث الأبوريجيني",
        "days": 15,
        "created_at": "2026-03-01T00:00:00.000Z"
      }
    ]
  }
}