{
  "version": 1,
  "country": "at",
  "language": "fr",
  "places": [
    {
      "place_id": "AT::achensee",
      "name": "Achensee",
      "cc": "AT",
      "language": "fr",
      "coords": [
        47.436,
        11.707
      ],
      "lat": 47.436,
      "lon": 11.707,
      "visits": [
        {
          "text": "Exploration du lac Achensee, le plus grand du Tyrol",
          "visit_duration_min": 75
        }
      ],
      "activities": [
        {
          "text": "Baignade, activités nautiques ou randonnée autour du lac"
        }
      ],
      "days_plan": [
        {
          "itin_id": "AT::autriche::roadtrip-famille-nature-et-culture",
          "itin_title": "Road Trip Autriche : Nature, Culture et Lacs Alpins",
          "day": 4
        }
      ],
      "rating": 6.1,
      "place_type": "nature",
      "suggested_days": 0.5
    },
    {
      "place_id": "AT::alpbach",
      "name": "Alpbach",
      "cc": "AT",
      "language": "fr",
      "coords": [
        47.39822,
        11.94364
      ],
      "lat": 47.39822,
      "lon": 11.94364,
      "visits": [
        {
          "text": "Village d’Alpbach (974 m) : architecture traditionnelle et ruelles fleuries",
          "visit_duration_min": 75
        },
        {
          "text": "Innsbruck (option) : Vieille ville, Toit d’Or, Bergisel en surplomb",
          "visit_duration_min": 75
        }
      ],
      "activities": [
        {
          "text": "Téléphérique alpin (AR) vers un point de vue panoramique"
        },
        {
          "text": "Randonnée familiale 10,4 km (D+≈360 m) sur alpages et belvédères"
        }
      ],
      "days_plan": [
        {
          "itin_id": "AT::eastern-alps::lacs-et-montagnes-7j",
          "itin_title": "Road Trip Autriche : Vienne, Salzbourg, Tyrol et Lacs Alpins",
          "day": 6
        }
      ],
      "rating": 7,
      "place_type": "village",
      "suggested_days": 0.5
    },
    {
      "place_id": "AT::bad-kleinkirchheim",
      "name": "Bad Kleinkirchheim",
      "cc": "AT",
      "language": "fr",
      "coords": [
        46.8167,
        13.8
      ],
      "lat": 46.8167,
      "lon": 13.8,
      "visits": [
        {
          "text": "Bad Kleinkirchheim est une station thermale et de ski à 1 100 m d'altitude dans les Nockberge. Ses sources thermales naturelles jaillissent à 36°C - découvertes en 1834 et utilisées depuis pour leurs propriétés curatives. Les Therme Römerbad et Therme St. Kathrein offrent piscines panoramiques extérieures, saunas alpins et soins de bien-être avec vue sur les sommets.",
          "visit_duration_min": 120
        },
        {
          "text": "La Nockalm-Straße traverse le Parc de Biosphère UNESCO des Nockberge sur 35 km avec 52 virages et 8 points de vue désignés. Les paysages arrondis et herbeux, sculptés par les glaciers quaternaires, abritent plus de 2 000 espèces végétales - une diversité botanique exceptionnelle liée au calcaire des Nockberge.",
          "visit_duration_min": 90
        }
      ],
      "activities": [
        {
          "text": "Détente aux thermes après la route panoramique. En hiver, Bad Kleinkirchheim propose 103 km de pistes avec 25 remontées mécaniques et accueille régulièrement des manches de Coupe du Monde de ski alpin sur la légendaire piste Franz Klammer."
        }
      ],
      "days_plan": [
        {
          "itin_id": "AT::carinthia::lakes-mountains-alpine-roads",
          "itin_title": "Circuit Carinthie Autriche : Lacs, Routes Alpines et Châteaux",
          "day": 21
        }
      ],
      "map_keywords": [
        "Bad Kleinkirchheim thermes Römerbad St Kathrein",
        "Nockalm Strasse route panoramique Nockberge",
        "Bad Kleinkirchheim station ski Coupe du Monde",
        "Biosphärenpark Nockberge UNESCO"
      ],
      "rating": 5.6,
      "place_type": "village",
      "suggested_days": 0.5
    },
    {
      "place_id": "AT::brand-vorarlberg",
      "name": "Brand Vorarlberg",
      "cc": "AT",
      "language": "fr",
      "coords": [
        47.1001,
        9.7289
      ],
      "lat": 47.1001,
      "lon": 9.7289,
      "visits": [
        {
          "text": "Vallée de Brandnertal dans le Vorarlberg, encaissée entre les massifs du Rätikon et du Bregenzerwaldgebirge. Le village de Brand à 1 037 m est le point de départ d'accès à plusieurs téléphériques et au Lünersee. Chalets traditionnels vorarlbergeois, fromageries d'alpage et panoramas dégagés.",
          "visit_duration_min": 45
        },
        {
          "text": "Lünersee (1 970 m), lac en forme de coeur entouré de parois calcaires avec vue directe sur la Schesaplana (2 965 m), point culminant du Rätikon. Classé comme la « Perle des Alpes », ses eaux turquoise contrastent avec les éboulis gris des falaises environnantes. Tour complète du lac : 6 km, 2h, facile.",
          "visit_duration_min": 150
        },
        {
          "text": "Lünerseebahn depuis Brand jusqu'au lac en 5 minutes, téléphérique ouvert de mi-mai à fin octobre. Les vues pendant la montée sur la vallée et les sommets du Rätikon sont déjà spectaculaires avant même d'atteindre le lac.",
          "visit_duration_min": 30
        }
      ],
      "activities": [
        {
          "text": "Randonnée vers la Totalphütte (2 385 m) depuis le Lünersee - 1h30 de montée supplémentaire pour atteindre ce refuge face aux glaciers de la Schesaplana. Niveau sportif, équipement montagne obligatoire au-delà de 2 200 m."
        },
        {
          "text": "Gorges de Bürser Schlucht (2h de parcours), sentier sur passerelles et ponts suspendus à travers des gorges taillées dans le calcaire avec cascades et formations rocheuses. Départ depuis Bürs (10 min de Brand). Spectaculaire et accessible pour tous."
        }
      ],
      "days_plan": [
        {
          "itin_id": "AT::autriche::two-weeks-explorers",
          "itin_title": "Autriche en trois semaines : Wachau, Alpes et Salzbourg",
          "day": 11
        }
      ],
      "rating": 5.2,
      "place_type": "village",
      "suggested_days": 0.5
    },
    {
      "place_id": "AT::dobratsch",
      "name": "Dobratsch",
      "cc": "AT",
      "language": "fr",
      "coords": [
        46.6017,
        13.6667
      ],
      "lat": 46.6017,
      "lon": 13.6667,
      "visits": [
        {
          "text": "La Villacher Alpenstrasse grimpe en 16,5 km jusqu'à 1 732 mètres sur le massif du Dobratsch, avec des points de vue désignés sur l'ensemble des lacs de Carinthie. Le Jardin Botanique Alpin, à mi-parcours, répertorie plus de 600 espèces végétales de haute montagne. Le nouveau belvédère de Rote Wand offre une vue panoramique exceptionnelle sur Villach et les Karawanken.",
          "visit_duration_min": 90
        },
        {
          "text": "La montée à pied depuis le parking terminal jusqu'au sommet du Dobratsch (2 166 m) prend 1h30. Le restaurant panoramique au sommet propose cuisine alpine et bières régionales avec toute la Carinthie étalée devant soi par beau temps.",
          "visit_duration_min": 90
        }
      ],
      "activities": [
        {
          "text": "Descente en soirée aux thermes de Warmbad Villach (KärntenTherme) pour une session bien-être après la journée en altitude. Les sources thermales naturelles à 29°C et les piscines extérieures panoramiques sont particulièrement appréciées au coucher du soleil."
        }
      ],
      "days_plan": [
        {
          "itin_id": "AT::carinthia::lakes-mountains-alpine-roads",
          "itin_title": "Circuit Carinthie Autriche : Lacs, Routes Alpines et Châteaux",
          "day": 11
        }
      ],
      "map_keywords": [
        "Villacher Alpenstrasse route panoramique Dobratsch",
        "Dobratsch jardin botanique alpin",
        "Rote Wand belvédère Dobratsch",
        "KärntenTherme Warmbad Villach"
      ],
      "rating": 2.9,
      "place_type": "nature",
      "suggested_days": 0.5
    },
    {
      "place_id": "AT::dreilandereck",
      "name": "Dreilandereck",
      "cc": "AT",
      "language": "fr",
      "coords": [
        46.5167,
        13.7167
      ],
      "lat": 46.5167,
      "lon": 13.7167,
      "visits": [
        {
          "text": "Le Dreiländereck est le point de rencontre géographique de l'Autriche, de l'Italie et de la Slovénie, accessible par télésiège depuis Arnoldstein en 15 minutes. Depuis la station supérieure, le panorama s'étend simultanément sur trois pays : les Alpes de Carinthie, les Dolomites frioulanes et les montagnes slovènes.",
          "visit_duration_min": 75
        },
        {
          "text": "Plusieurs sentiers de randonnée partent de la station supérieure : promenades faciles sur les crêtes ou randonnées d'une journée pour les plus sportifs. La terrasse du chalet-refuge propose des Jausen (collations alpines) avec vue sur les sommets des trois pays.",
          "visit_duration_min": 60
        }
      ],
      "activities": [
        {
          "text": "Le télésiège du Dreiländereck est inclus dans la Kärnten Card. Ouvert de fin mai à fin septembre. La Kärnten Card donne accès à plus de 100 attractions en Carinthie - rentable dès 4-5 utilisations."
        }
      ],
      "days_plan": [
        {
          "itin_id": "AT::carinthia::lakes-mountains-alpine-roads",
          "itin_title": "Circuit Carinthie Autriche : Lacs, Routes Alpines et Châteaux",
          "day": 10
        }
      ],
      "map_keywords": [
        "Dreiländereck frontière Autriche Italie Slovénie",
        "Arnoldstein télésiège Dreiländereck",
        "point de rencontre trois pays Carinthie"
      ],
      "rating": 7.2,
      "place_type": "site",
      "suggested_days": 0.2
    },
    {
      "place_id": "AT::durnstein",
      "name": "Durnstein",
      "cc": "AT",
      "language": "fr",
      "coords": [
        48.3939,
        15.5228
      ],
      "lat": 48.3939,
      "lon": 15.5228,
      "visits": [
        {
          "text": "Village médiéval de Dürnstein, véritable joyau de la Wachau. Ses ruelles pavées aux maisons baroques pastel, ses fontaines et ses caves à vin se resserrent autour de l'Abbaye augustinienne dont la tour bleue est le symbole de la vallée - visible depuis des kilomètres le long du Danube.",
          "visit_duration_min": 60
        },
        {
          "text": "Ruines du château de Dürnstein perché à 230 m au-dessus du village. C'est ici que Richard Coeur de Lion fut emprisonné en 1192 après la Troisième Croisade, retenu par le duc Léopold V d'Autriche. La rançon de 150 000 marks d'argent équivalait à deux fois le revenu annuel de l'Angleterre. Montée de 20-30 min depuis le village, accès libre.",
          "visit_duration_min": 75
        },
        {
          "text": "Abbaye de Melk (UNESCO), forteresse bénédictine baroque dominant le Danube depuis un éperon rocheux à 60 m de hauteur. Fondée au XIe siècle, redessinée au XVIIIe dans un style baroque flamboyant, elle abrite une bibliothèque de 100 000 volumes, une église dorée et une terrasse panoramique sur la Wachau. Des moines bénédictins y vivent et travaillent encore aujourd'hui.",
          "visit_duration_min": 120
        },
        {
          "text": "Vignobles en terrasses de la Wachau entre Melk et Krems, 30 km de paysage classé UNESCO depuis 2000. Trois appellations protégées : Steinfeder (léger), Federspiel (intermédiaire) et Smaragd (grande garde). Le Grüner Veltliner et le Riesling de ces coteaux calcaires sont parmi les meilleurs vins blancs d'Autriche.",
          "visit_duration_min": 45
        }
      ],
      "activities": [
        {
          "text": "Croisière courte sur le Danube entre Dürnstein et Spitz (30 min) avec la compagnie DDSG ou Brandner. Vue unique sur les falaises viticoles, les ruines de châteaux et les villages cachés dans les anses. Disponible mai-octobre, départs toutes les heures depuis l'embarcadère de Dürnstein."
        },
        {
          "text": "Dégustation de Grüner Veltliner chez un vigneron local. Les Buschenschenken (tavernes de vignerons signalées par un rameau de pin) servent leur propre production accompagnée de charcuteries et de fromages régionaux. Domaine Tegernseerhof et Weingut Knoll figurent parmi les plus réputés."
        }
      ],
      "days_plan": [
        {
          "itin_id": "AT::autriche::two-weeks-explorers",
          "itin_title": "Autriche en trois semaines : Wachau, Alpes et Salzbourg",
          "day": 2
        }
      ],
      "rating": 8.9,
      "place_type": "village",
      "suggested_days": 0.3
    },
    {
      "place_id": "AT::ehrwald",
      "name": "Ehrwald",
      "cc": "AT",
      "language": "fr",
      "coords": [
        47.4053,
        10.9097
      ],
      "lat": 47.4053,
      "lon": 10.9097,
      "visits": [
        {
          "text": "Village d'Ehrwald à 994 m dans la vallée de l'Außerfern, au pied du massif du Wetterstein. Bourg tyrolien authentique avec ses fermes à balcons fleuris, son église baroque et sa vue directe sur la face nord de la Zugspitze (2 962 m). Point de départ côté autrichien pour l'ascension du plus haut sommet d'Allemagne.",
          "visit_duration_min": 45
        },
        {
          "text": "Zugspitze (2 962 m) par le Tiroler Zugspitzbahn, téléphérique autrichien partant d'Ehrwald et atteignant le sommet en 10 minutes dans des cabines de 100 personnes. Au sommet : vue sur 4 pays (Autriche, Allemagne, Suisse, Italie), musée Faszination Zugspitze, restaurant panoramique et le glacier Schneeferner.",
          "visit_duration_min": 180
        },
        {
          "text": "Seebensee (1 657 m), lac de montagne dans un cirque rocheux au pied de la Zugspitze. Accessible par randonnée depuis Ehrwald (2h30, 650 m de dénivelé) ou par l'Ehrwalder Almbahn. Eaux glacées aux reflets verts, rochers calcaires, silence alpin - l'un des plus beaux cadres du massif du Wetterstein.",
          "visit_duration_min": 120
        }
      ],
      "activities": [
        {
          "text": "Randonnée Coburger Hütte (1 917 m) depuis le Seebensee - 30 minutes supplémentaires depuis le lac pour atteindre ce refuge avec vue sur le Drachensee. Niveau intermédiaire, sentier bien balisé, refuge ouvert de juin à octobre."
        },
        {
          "text": "Musée BAHNORAMA anno 1926 dans la station aval du téléphérique Zugspitzbahn, retraçant 100 ans d'histoire des téléphériques alpins avec maquettes, documents d'archives et film d'époque. Entrée incluse avec le billet du téléphérique."
        }
      ],
      "days_plan": [
        {
          "itin_id": "AT::autriche::two-weeks-explorers",
          "itin_title": "Autriche en trois semaines : Wachau, Alpes et Salzbourg",
          "day": 9
        }
      ],
      "rating": 6.3,
      "place_type": "village",
      "suggested_days": 0.5
    },
    {
      "place_id": "AT::faaker-see",
      "name": "Faaker See",
      "cc": "AT",
      "language": "fr",
      "coords": [
        46.575,
        13.9167
      ],
      "lat": 46.575,
      "lon": 13.9167,
      "visits": [
        {
          "text": "Le Faaker See est l'un des plus beaux lacs de Carinthie : ses eaux d'un turquoise profond atteignent 27°C en été. Ce lac de 2,5 km de long est caractérisé par sa petite île centrale qui reste l'une des images les plus photographiées de la région. Sa taille modeste garantit un réchauffement rapide et des conditions de baignade idéales.",
          "visit_duration_min": 75
        },
        {
          "text": "La montée à Hochhinauf-Taborhöhe offre les meilleures vues plongeantes sur le Faaker See et son île. L'accès par les sentiers forestiers prend environ 45 minutes depuis les rives du lac.",
          "visit_duration_min": 60
        }
      ],
      "activities": [
        {
          "text": "Location de matériel nautique sur les plages aménagées de Drobollach et Egg am Faaker See : pédalos, kayaks, planches à pagaie. Un sentier de promenade longe entièrement le pourtour du lac en 1h30."
        }
      ],
      "days_plan": [
        {
          "itin_id": "AT::carinthia::lakes-mountains-alpine-roads",
          "itin_title": "Circuit Carinthie Autriche : Lacs, Routes Alpines et Châteaux",
          "day": 7
        }
      ],
      "map_keywords": [
        "Faaker See lac Carinthie",
        "Taborhöhe point de vue Faaker See",
        "Faaker See île centrale",
        "Drobollach plage Faaker See"
      ],
      "rating": 4.7,
      "place_type": "nature",
      "suggested_days": 0.5
    },
    {
      "place_id": "AT::ferlach",
      "name": "Ferlach",
      "cc": "AT",
      "language": "fr",
      "coords": [
        46.4757,
        14.2493
      ],
      "lat": 46.4757,
      "lon": 14.2493,
      "visits": [
        {
          "text": "La Tscheppaschlucht est l'une des plus belles gorges de Carinthie. L'eau bouillonne entre des parois rocheuses escarpées, formant cascades et tourbillons. Le sentier bien équipé - passerelles métalliques, échelles, escaliers taillés dans la roche - longe la rivière sur environ 2 km pour 2 heures d'exploration. Le secteur du Teufelsbrücke (Pont du Diable) offre les vues les plus dramatiques sur les cascades.",
          "visit_duration_min": 120
        },
        {
          "text": "La vallée de Bodental, accessible depuis la sortie de la gorge, abrite le Meerauge - un petit lac aux couleurs bleu-vert intenses et à l'eau exceptionnellement limpide, alimenté par des sources souterraines. La Märchenwiese (prairie aux Fées), à 20 minutes de marche, est une prairie alpine entourée de parois boisées d'une sérénité remarquable.",
          "visit_duration_min": 75
        }
      ],
      "activities": [
        {
          "text": "Combinaison gorge + vallée de Bodental en journée complète. Prévoir chaussures de randonnée avec semelles antidérapantes - le sentier de la Tscheppaschlucht est humide en permanence. Pique-nique possible sur les pelouses de la Märchenwiese."
        }
      ],
      "days_plan": [
        {
          "itin_id": "AT::carinthia::lakes-mountains-alpine-roads",
          "itin_title": "Circuit Carinthie Autriche : Lacs, Routes Alpines et Châteaux",
          "day": 9
        }
      ],
      "map_keywords": [
        "Tscheppaschlucht gorge Ferlach Carinthie",
        "Teufelsbrücke pont du diable gorge",
        "Bodental Meerauge lac vert Ferlach",
        "Märchenwiese prairie fées Bodental"
      ],
      "rating": 3.9,
      "place_type": "small_city",
      "suggested_days": 0.2
    },
    {
      "place_id": "AT::filzmoos",
      "name": "Filzmoos",
      "cc": "AT",
      "language": "fr",
      "coords": [
        47.4344,
        13.5219
      ],
      "lat": 47.4344,
      "lon": 13.5219,
      "visits": [
        {
          "text": "Village de Filzmoos à 1 057 m d'altitude, entre les deux pics du Bischofsmütze (la « mitre d'évêque ») et le massif du Dachstein. Ce hameau alpin authentique du Pays de Salzbourg a été labellisé « Austrian Hiking Village » et concentre 250 km de sentiers balisés dans un rayon de 10 km.",
          "visit_duration_min": 45
        },
        {
          "text": "Église paroissiale de pèlerinage de Filzmoos, édifice gothique du XVe siècle dédié à saint Pierre et saint Paul. Elle abrite la sculpture du Filzmooser Kindl, un Enfant Jésus gothique coloré entouré d'une auréole dorée sculptée - l'un des 17 « lieux de puissance » (Power Spots) du village.",
          "visit_duration_min": 30
        },
        {
          "text": "Panorama sur le Bischofsmütze (2 454 m) depuis le village, ce sommet aux deux pics jumeaux qui dominent toute la région de Schladming-Dachstein. Sa silhouette rappelle une mitre épiscopale, ce qui lui a valu son nom. Il fait partie du massif des Gosaukamm, dans les Alpes calcaires.",
          "visit_duration_min": 30
        },
        {
          "text": "Téléphérique du Dachstein Krippenstein depuis Obertraun, deux tronçons successifs montant à 2 109 m. Depuis le sommet, vue panoramique sur les Alpes calcaires, le lac de Hallstatt et les gorges du Traun. Prévoir des vêtements chauds même en été - la température chute de 10 à 15°C.",
          "visit_duration_min": 90
        },
        {
          "text": "Plateforme 5 Fingers à 2 109 m, cinq passerelles en acier s'avançant dans le vide au-dessus d'une falaise de 400 m. Chacune a une forme différente - l'une a un plancher en verre transparent. Depuis le téléphérique, 20 minutes de marche sur un sentier balisé.",
          "visit_duration_min": 60
        },
        {
          "text": "Grotte de glace du Dachstein (Rieseneishöhle), visite guidée de 50 minutes dans des galeries de glace formées depuis des millénaires. La Cathédrale du roi Arthur et le Palais des Glaces avec son cône de glace de 9 m de hauteur sont les points forts. Température permanente de -2°C - veste obligatoire.",
          "visit_duration_min": 75
        },
        {
          "text": "Grotte Mammouth (Mammuthöhle), l'une des plus grandes grottes d'Europe avec 70 km explorés. Galeries de calcaire aux formations spectaculaires creusées par les eaux sur des millénaires. Visite guidée indépendante de la grotte de glace - billet combiné recommandé.",
          "visit_duration_min": 60
        }
      ],
      "activities": [
        {
          "text": "Randonnée d'arrivée vers la Hofpürglhütte (1 705 m), refuge alpin au pied du Bischofsmütze. Depuis le parking Unterhofalm, comptez 2 heures aller pour 600 m de dénivelé. Vue spectaculaire sur le massif Gosaukamm et le Dachstein. Refuge ouvert mi-mai à fin octobre."
        },
        {
          "text": "Téléphérique Papageno depuis le centre du village pour accéder aux pâturages d'altitude et aux sentiers panoramiques sans effort. Point de départ de nombreuses randonnées familiales en été, domaine skiable en hiver."
        },
        {
          "text": "Randonnée sur le Dachstein Rundwanderweg, circuit de 3 jours qui fait le tour du massif. Même une simple demi-journée sur le tronçon Krippenstein-Schönbergalm offre des vues grandioses sur les glaciers. Sentier bien balisé, niveau intermédiaire."
        },
        {
          "text": "Hallstatt (20 min depuis Filzmoos) : le village lacustre le plus photographié d'Autriche, pressé entre lac et falaises. Mine de sel vieille de 7 000 ans (UNESCO), Beinhaus (ossuaire) décoré de crânes peints, et vue depuis la plateforme Welterbeblick à 360 m au-dessus du lac."
        }
      ],
      "days_plan": [
        {
          "itin_id": "AT::autriche::two-weeks-explorers",
          "itin_title": "Autriche en trois semaines : Wachau, Alpes et Salzbourg",
          "day": 3
        },
        {
          "itin_id": "AT::autriche::two-weeks-explorers",
          "itin_title": "Autriche en trois semaines : Wachau, Alpes et Salzbourg",
          "day": 4
        }
      ],
      "rating": 7.5,
      "place_type": "village",
      "suggested_days": 0.5
    },
    {
      "place_id": "AT::flattach",
      "name": "Flattach",
      "cc": "AT",
      "language": "fr",
      "coords": [
        46.9333,
        13.15
      ],
      "lat": 46.9333,
      "lon": 13.15,
      "visits": [
        {
          "text": "La Raggaschlucht, dans le Parc National des Hohe Tauern près de Flattach, est l'une des gorges les plus spectaculaires de Carinthie. Des passerelles en bois guident le visiteur le long de la rivière à travers des rapides et des cascades successives, sur un parcours de 800 mètres montant jusqu'à la chute principale. L'encaissement des parois et la végétation de fougères et de mousses créent une atmosphère de forêt primaire.",
          "visit_duration_min": 75
        },
        {
          "text": "La Groppensteinschlucht, à quelques kilomètres, est une gorge de 2,5 km avec des sentiers en bois longeant la rivière sauvage. Le parcours facile convient aux familles et prend 1h30 à 2h. En saison, des visites nocturnes permettent de découvrir la gorge magnifiquement illuminée après la tombée de la nuit.",
          "visit_duration_min": 90
        }
      ],
      "activities": [
        {
          "text": "Les deux gorges peuvent se visiter dans la même journée. Chaussures imperméables ou de randonnée indispensables - les passerelles sont aspergées en permanence. Ouverture de mai à octobre."
        }
      ],
      "days_plan": [
        {
          "itin_id": "AT::carinthia::lakes-mountains-alpine-roads",
          "itin_title": "Circuit Carinthie Autriche : Lacs, Routes Alpines et Châteaux",
          "day": 16
        }
      ],
      "map_keywords": [
        "Raggaschlucht gorge Flattach Hohe Tauern",
        "Groppensteinschlucht gorge Carinthie",
        "Flattach Parc National Hohe Tauern",
        "gorges illuminées Groppensteinschlucht nuit"
      ],
      "rating": 4.1,
      "place_type": "village",
      "suggested_days": 0.2
    },
    {
      "place_id": "AT::friesach",
      "name": "Friesach",
      "cc": "AT",
      "language": "fr",
      "coords": [
        46.95,
        14.4083
      ],
      "lat": 46.95,
      "lon": 14.4083,
      "visits": [
        {
          "text": "Friesach est la plus ancienne ville de Carinthie, attestée depuis 860 ap. J.-C. et la cité médiévale la mieux préservée du sud de l'Autriche. Son centre historique reste entouré de remparts du XIIe siècle pratiquement intacts sur 1,8 kilomètre - une rareté dans les Alpes. La Hauptplatz est bordée de maisons gothiques et Renaissance dont beaucoup conservent leurs arcades d'origine et leurs cours intérieures médiévales.",
          "visit_duration_min": 75
        },
        {
          "text": "Le château de Petersberg, érigé par les évêques de Salzbourg au XIIe siècle sur la colline dominant la ville, abrite le musée municipal. Collections archéologiques, art sacré et reconstitutions de la vie médiévale retracent l'histoire de cette ville qui fut pendant des siècles la plus importante de Carinthie.",
          "visit_duration_min": 75
        },
        {
          "text": "L'église paroissiale romane du XIIe siècle conserve ses fresques gothiques et son autel en bois sculpté. Le couvent dominicain adjacent, fondé en 1217, est l'un des plus anciens couvents de langue germanique encore en activité.",
          "visit_duration_min": 45
        }
      ],
      "activities": [
        {
          "text": "Friesach abrite un projet unique d'archéologie expérimentale : la reconstruction d'un château médiéval en utilisant exclusivement des techniques et des outils du XIIIe siècle. Les visiteurs peuvent observer en direct le travail des artisans et comprendre comment on construisait une forteresse il y a 800 ans."
        }
      ],
      "days_plan": [
        {
          "itin_id": "AT::carinthia::lakes-mountains-alpine-roads",
          "itin_title": "Circuit Carinthie Autriche : Lacs, Routes Alpines et Châteaux",
          "day": 3
        }
      ],
      "map_keywords": [
        "Friesach remparts médiévaux Carinthie",
        "Hauptplatz Friesach maisons gothiques",
        "Château Petersberg Friesach musée",
        "Friesach plus ancienne ville Carinthie",
        "archéologie expérimentale château Friesach"
      ],
      "rating": 3.4,
      "place_type": "small_city",
      "suggested_days": 0.3
    },
    {
      "place_id": "AT::graz",
      "name": "Graz",
      "cc": "AT",
      "language": "fr",
      "coords": [
        47.0707,
        15.4395
      ],
      "lat": 47.0707,
      "lon": 15.4395,
      "visits": [
        {
          "text": "La vieille ville de Graz (Grazer Altstadt), inscrite au patrimoine mondial de l'UNESCO, déploie ses façades baroques et Renaissance autour de la Hauptplatz - la grande place centrale. Les cours intérieures cachées, les ruelles pavées en pente et les passages discrets forment un labyrinthe médiéval que chaque tournant renouvelle. Rendez-vous à la Herrengasse pour ses maisons à arcades et ses façades sculptées.",
          "visit_duration_min": 75
        },
        {
          "text": "Le Schlossberg est la colline boisée qui domine Graz depuis son centre, autrefois couronnée d'une forteresse médiévale démantelée par Napoléon en 1809. Il n'en reste que la tour de l'Horloge (Uhrturm), emblème de la ville, dont l'horloge a la particularité d'afficher l'heure à l'envers depuis 1712 : la grande aiguille indique les heures. Montez en funiculaire ou par les 260 marches - la vue sur les toits rouges et les clochers de Graz est panoramique.",
          "visit_duration_min": 60
        },
        {
          "text": "Le Kunsthaus Graz, surnommé affectueusement le « Friendly Alien », est une bulle bleutée au look de vaisseau spatial posée sur les rives de la Mur. Conçu par Peter Cook et Colin Fournier en 2003 pour la candidature de Graz comme capitale européenne de la culture, il présente des expositions d'art contemporain avec des installations spectaculaires. Même les enfants restent fascinés par ses formes organiques et ses « nozzles » - ces hublots-antennes orientés vers la ville.",
          "visit_duration_min": 60
        },
        {
          "text": "L'Armurerie styrienne (Landeszeughaus) conserve plus de 32 000 armures, épées, piques et boulets de canon - la plus grande collection d'armures historiques d'Autriche. Les salles entières d'armures d'apparat du XVIe siècle, encore rangées comme si leurs propriétaires allaient revenir, créent un spectacle impressionnant. Parfait pour captiver les enfants avec des récits de chevalerie.",
          "visit_duration_min": 60
        }
      ],
      "activities": [
        {
          "text": "Grimpez au sommet du Schlossberg en funiculaire, et une fois en haut, repérez le toboggan géant souterrain taillé dans la roche qui redescend les visiteurs vers la vieille ville. Une attraction insolite et appréciée des enfants, creusée dans le noyau rocheux de la colline."
        },
        {
          "text": "Flânerie sur les marchés de la Kaiser-Josef-Platz et de la Hauptplatz, où les producteurs styriens exposent fruits, légumes, fromages et l'incontournable Kürbiskernöl - l'huile de pépins de courge verte, spécialité régionale au goût de noisette grillée, qui se verse sur les salades et les fromages."
        }
      ],
      "days_plan": [
        {
          "itin_id": "AT::austria-family-roadtrip",
          "itin_title": "Voyage Autriche en Famille : Montagnes, Lacs et Palais Impériaux",
          "day": 4
        }
      ],
      "map_keywords": [
        "Schlossberg Graz tour de l'horloge",
        "Altstadt Graz UNESCO",
        "Kunsthaus Graz Friendly Alien",
        "Hauptplatz Graz",
        "Schloss Eggenberg Graz",
        "Murinsel Graz",
        "Landeszeughaus armurerie Graz"
      ],
      "rating": 9.7,
      "place_type": "metropolis",
      "suggested_days": 1.5
    },
    {
      "place_id": "AT::gurk",
      "name": "Gurk",
      "cc": "AT",
      "language": "fr",
      "coords": [
        46.875,
        14.2917
      ],
      "lat": 46.875,
      "lon": 14.2917,
      "visits": [
        {
          "text": "La cathédrale de Gurk, consacrée en 1200, est considérée comme l'édifice religieux roman le plus important d'Autriche. Sa façade à deux tours de 44 mètres de hauteur et son intérieur recouvert de fresques romanes et gothiques sur plus de 1 000 m² en font un monument exceptionnel. La crypte, soutenue par 100 colonnes aux chapiteaux sculptés tous différents, abrite le sarcophage de la bienheureuse Emma - c'est l'un des exemples les plus purs d'architecture romane du XIe siècle en Europe centrale.",
          "visit_duration_min": 90
        },
        {
          "text": "Le musée diocésain, dans le palais épiscopal adjacent, expose l'une des plus riches collections d'art sacré médiéval d'Autriche : vêtements liturgiques, reliquaires en or et le calice de Gurk du XIIe siècle aux émaux cloisonnés. La bibliothèque conserve des manuscrits enluminés des XIIIe-XVe siècles.",
          "visit_duration_min": 60
        }
      ],
      "activities": [
        {
          "text": "L'autel baroque de Michael Hönel (1740) domine le choeur de la cathédrale. Le trésor de Gurk, exposé dans une salle adjacente, rassemble sept siècles d'orfèvrerie sacrée - une visite qui complète idéalement la cathédrale romane."
        }
      ],
      "days_plan": [
        {
          "itin_id": "AT::carinthia::lakes-mountains-alpine-roads",
          "itin_title": "Circuit Carinthie Autriche : Lacs, Routes Alpines et Châteaux",
          "day": 4
        }
      ],
      "map_keywords": [
        "Cathédrale de Gurk romane Autriche",
        "crypte Gurk 100 colonnes chapiteaux",
        "musée diocésain Gurk art sacré",
        "abbaye Gurk Carinthie",
        "Gurk chef-d'oeuvre roman"
      ],
      "rating": 2.6,
      "place_type": "village",
      "suggested_days": 0.2
    },
    {
      "place_id": "AT::hallstatt",
      "name": "Hallstatt",
      "cc": "AT",
      "language": "fr",
      "coords": [
        47.5622,
        13.6493
      ],
      "lat": 47.5622,
      "lon": 13.6493,
      "visits": [
        {
          "text": "Hallstätter See et village de Hallstatt (UNESCO)",
          "visit_duration_min": 75
        },
        {
          "text": "Plateforme panoramique Welterbeblick (vue sur le lac et le village)",
          "visit_duration_min": 75
        }
      ],
      "activities": [
        {
          "text": "Randonnée Gosauseen : boucle 15 km (D+≈458 m) autour du Vorderer Gosausee"
        },
        {
          "text": "Pause plage/lac au Hallstätter See"
        }
      ],
      "days_plan": [
        {
          "itin_id": "AT::autriche::roadtrip-famille-nature-et-culture",
          "itin_title": "Road Trip Autriche : Nature, Culture et Lacs Alpins",
          "day": 3
        },
        {
          "itin_id": "AT::eastern-alps::lacs-et-montagnes-7j",
          "itin_title": "Road Trip Autriche : Vienne, Salzbourg, Tyrol et Lacs Alpins",
          "day": 4
        }
      ],
      "rating": 9.1,
      "place_type": "village",
      "suggested_days": 0.5
    },
    {
      "place_id": "AT::heiligenblut",
      "name": "Heiligenblut",
      "cc": "AT",
      "language": "fr",
      "coords": [
        47.04,
        12.8433
      ],
      "lat": 47.04,
      "lon": 12.8433,
      "visits": [
        {
          "text": "La Route Alpine du Grossglockner (Grossglockner Hochalpenstraße) est l'une des plus belles routes panoramiques du monde. Cet itinéraire de 48 km serpente à travers le Parc National des Hohe Tauern avec 36 belvédères aménagés, atteignant le col de l'Edelweiß à 2 571 m. Construite entre 1930 et 1935, elle reste l'un des grands chefs-d'oeuvre du génie civil autrichien.",
          "visit_duration_min": 120
        },
        {
          "text": "Le Kaiser-Franz-Josefs-Höhe offre une vue directe sur le glacier de Pasterze (8,4 km de long, plus grand glacier des Alpes orientales) et le Grossglockner (3 798 m, plus haut sommet d'Autriche). Des marmottes en liberté, des bouquetins et des aigles royaux peuplent les abords du belvédère. Un funiculaire descend jusqu'au front du glacier.",
          "visit_duration_min": 90
        },
        {
          "text": "Heiligenblut, au pied de la route côté carinthien, est un village alpin d'une beauté classique avec son église gothique à clocher pointu encadrée par les glaciers. La cascade du Jungfernsprung (130 m), visible depuis le village, doit son nom à une légende médiévale.",
          "visit_duration_min": 45
        }
      ],
      "activities": [
        {
          "text": "La route est à péage (tarif voiture). Ouverture de mai à novembre selon enneigement. Prévoir vêtements chauds même en été - la différence de température entre la vallée et le col peut dépasser 15°C. Le centre des visiteurs de Mallnitz présente la faune et la flore du Parc National."
        }
      ],
      "days_plan": [
        {
          "itin_id": "AT::carinthia::lakes-mountains-alpine-roads",
          "itin_title": "Circuit Carinthie Autriche : Lacs, Routes Alpines et Châteaux",
          "day": 18
        }
      ],
      "map_keywords": [
        "Grossglockner Hochalpenstrasse route alpine",
        "Kaiser-Franz-Josefs-Höhe glacier Pasterze",
        "Heiligenblut église Grossglockner",
        "Jungfernsprung cascade Heiligenblut",
        "Edelweissalpe col panoramique"
      ],
      "rating": 4.7,
      "place_type": "village",
      "suggested_days": 0.3
    },
    {
      "place_id": "AT::imst",
      "name": "Imst",
      "cc": "AT",
      "language": "fr",
      "coords": [
        47.2382,
        10.7391
      ],
      "lat": 47.2382,
      "lon": 10.7391,
      "visits": [
        {
          "text": "Randonnée dans les gorges de Rosengartenschlucht à Imst",
          "visit_duration_min": 75
        }
      ],
      "activities": [
        {
          "text": "Exploration libre d’Imst et de ses environs alpins"
        }
      ],
      "days_plan": [
        {
          "itin_id": "AT::autriche::roadtrip-famille-nature-et-culture",
          "itin_title": "Road Trip Autriche : Nature, Culture et Lacs Alpins",
          "day": 7
        }
      ],
      "rating": 4.7,
      "place_type": "medium_city",
      "suggested_days": 0.5
    },
    {
      "place_id": "AT::innsbruck",
      "name": "Innsbruck",
      "cc": "AT",
      "language": "fr",
      "coords": [
        47.2692,
        11.4041
      ],
      "lat": 47.2692,
      "lon": 11.4041,
      "visits": [
        {
          "text": "Petit Toit d'Or (Goldenes Dachl), balcon couvert de 2 657 tuiles de cuivre doré construit en 1500 pour Maximilien Ier de Habsbourg. Cette loge d'honneur au-dessus de la vieille ville permettait à l'empereur d'assister aux tournois depuis son palais. C'est l'emblème absolu d'Innsbruck.",
          "visit_duration_min": 45
        },
        {
          "text": "Vieille ville d'Innsbruck (Altstadt), ensemble médiéval préservé entre le Toit d'Or et la Nordkette. Ruelles pavées, maisons aux façades baroques colorées, la Rue Herzog-Friedrich avec ses arcades gothiques et la maison Helbling au stuc baroque exubérant du XVIIIe siècle.",
          "visit_duration_min": 60
        },
        {
          "text": "Palais Hofburg d'Innsbruck, résidence d'été des Habsbourg reconstruite par Marie-Thérèse au XVIIIe siècle en style baroque tardif. La Salle des Géants avec ses portraits en taille réelle des 22 enfants de l'impératrice est particulièrement impressionnante. Audioguide inclus dans l'entrée.",
          "visit_duration_min": 75
        },
        {
          "text": "Nordkettenbahn, funiculaire et téléphériques conçus par Zaha Hadid reliant le centre d'Innsbruck à Seegrube (1 905 m) puis Hafelekar (2 256 m) en 30 minutes depuis la vieille ville. Vue aérienne complète sur Innsbruck et la vallée de l'Inn depuis les sommets du Karwendel.",
          "visit_duration_min": 150
        },
        {
          "text": "Hofkirche (Église de la Cour), mausolée de Maximilien Ier avec son cénotaphe entouré de 28 statues en bronze de 2 m surnommées les « bonshommes noirs ». Ces géants de bronze représentent ancêtres, alliés et personnages légendaires de la maison de Habsbourg.",
          "visit_duration_min": 60
        },
        {
          "text": "Château d'Ambras (4 km au sud d'Innsbruck), Renaissance italienne construite par l'archiduc Ferdinand II dans les années 1560. Abrite trois musées : la collection d'armures (400 pièces, l'une des meilleures d'Europe), la Wunderkammer (chambre des merveilles) et la galerie de portraits des Habsbourg. La Salle espagnole (43 m de long) est l'un des intérieurs Renaissance les plus importants d'Autriche.",
          "visit_duration_min": 120
        },
        {
          "text": "Mondes de Cristal Swarovski (Kristallwelten) à Wattens, 20 km à l'est d'Innsbruck. Fondée en 1895, l'usine Swarovski crée un parc culturel autour du cristal avec installations artistiques géantes, jardins de sculptures et boutique musée. Navette depuis Innsbruck en 30 min.",
          "visit_duration_min": 120
        }
      ],
      "activities": [
        {
          "text": "Ascension au Bergisel, tremplin olympique conçu par Zaha Hadid (2002) avec tour panoramique à 50 m. Vue imprenable sur Innsbruck et les Alpes depuis la tour vitrée. Restaurant au sommet accessible par ascenseur. Deux Jeux Olympiques s'y sont disputés (1964 et 1976)."
        },
        {
          "text": "Zoo Alpin du Bergisel (2 000 animaux de l'arc alpin, plus haut zoo d'Europe à 750 m), accessible depuis le Bergisel. Loups, lynx, ours bruns et aigles royaux dans des enclos ouverts sur le panorama alpin. Inclus dans l'Innsbruck Card."
        },
        {
          "text": "Randonnée sur le Nockspitze (2 404 m) depuis la station Mutteralmbahn (1 620 m) au-dessus de Mutters/Natters, accessible depuis Innsbruck en tramway et bus. 800 m de dénivelé supplémentaire, panorama sans égal sur Innsbruck. Niveau intermédiaire-sportif."
        },
        {
          "text": "Gastronomie innsbruckoise dans les restaurants et Wirtshäuser (auberges) du centre historique. Incontournables : Apfelstrudel au Strudelcafé Kröll (Innrain), Tiroler Gröstl (poêlée de pommes de terre, lard et oeuf) et Speckknödel (quenelles au lard) arrosés d'une bière locale de la Brasserie Stiegl."
        }
      ],
      "days_plan": [
        {
          "itin_id": "AT::autriche::roadtrip-famille-nature-et-culture",
          "itin_title": "Road Trip Autriche : Nature, Culture et Lacs Alpins",
          "day": 5
        },
        {
          "itin_id": "AT::austria-family-roadtrip",
          "itin_title": "Voyage Autriche en Famille : Montagnes, Lacs et Palais Impériaux",
          "day": 1
        },
        {
          "itin_id": "AT::autriche::two-weeks-explorers",
          "itin_title": "Autriche en trois semaines : Wachau, Alpes et Salzbourg",
          "day": 12
        },
        {
          "itin_id": "AT::autriche::two-weeks-explorers",
          "itin_title": "Autriche en trois semaines : Wachau, Alpes et Salzbourg",
          "day": 13
        }
      ],
      "rating": 9.4,
      "place_type": "large_city",
      "suggested_days": 1.5
    },
    {
      "place_id": "AT::klagenfurt",
      "name": "Klagenfurt",
      "cc": "AT",
      "language": "fr",
      "coords": [
        46.6247,
        14.3089
      ],
      "lat": 46.6247,
      "lon": 14.3089,
      "visits": [
        {
          "text": "Klagenfurt am Wörthersee, capitale de la Carinthie, s'articule autour de l'Alter Platz - sa place principale entourée de façades Renaissance et Art nouveau à l'italienne. La fontaine du Dragon (Lindwurmbrunnen, 1590) trône au centre : cette créature mythique est l'emblème de la ville depuis le Moyen Âge, quand les habitants croyaient qu'un dragon habitait les marécages où fut construite Klagenfurt.",
          "visit_duration_min": 75
        },
        {
          "text": "Le Landhaus, chef-d'oeuvre Renaissance du XVIe siècle, abrite la salle des armoiries avec 665 écussons peints représentant les familles nobles de Carinthie. Sa cour intérieure à double galerie d'arcades est l'une des plus élégantes d'Autriche.",
          "visit_duration_min": 60
        },
        {
          "text": "Le MMKK (Museum Moderner Kunst Kärnten), installé dans le château de Klagenfurt, présente l'une des collections d'art contemporain les plus importantes d'Autriche, du début du modernisme aux installations les plus récentes.",
          "visit_duration_min": 75
        },
        {
          "text": "Minimundus, sur les rives du Wörthersee, expose plus de 160 reproductions miniatures au 1/25e des monuments les plus célèbres du monde. La Tour Eiffel, le Taj Mahal, le Colisée ou la Sagrada Família côtoient des bâtiments autrichiens dans des jardins soigneusement entretenus.",
          "visit_duration_min": 60
        },
        {
          "text": "La cascade de Wildenstein, au sud de la Carinthie près de Rosen, est une conclusion naturelle à la grande boucle carinthienne. Accessible en 20 minutes de montée depuis le parking, une plateforme d'observation en bois offre des vues directes sur la chute d'eau dévalant la paroi rocheuse. L'entrée est gratuite.",
          "visit_duration_min": 60
        }
      ],
      "activities": [
        {
          "text": "Promenade en soirée sur les berges du Wörthersee depuis le centre-ville. La promenade longe le lac sur plusieurs kilomètres, avec vue sur les Alpes carinthiennes en toile de fond et les villas Belle Époque construites par l'aristocratie austro-hongroise."
        },
        {
          "text": "Retour à Klagenfurt (80 km, 1h) pour la fin du circuit. La cascade de Wildenstein, à mi-chemin, sert de halte finale idéale avant de rejoindre l'aéroport ou la gare de Klagenfurt."
        }
      ],
      "days_plan": [
        {
          "itin_id": "AT::carinthia::lakes-mountains-alpine-roads",
          "itin_title": "Circuit Carinthie Autriche : Lacs, Routes Alpines et Châteaux",
          "day": 1
        },
        {
          "itin_id": "AT::carinthia::lakes-mountains-alpine-roads",
          "itin_title": "Circuit Carinthie Autriche : Lacs, Routes Alpines et Châteaux",
          "day": 22
        }
      ],
      "map_keywords": [
        "Alter Platz Klagenfurt vieille ville",
        "Landhaus Klagenfurt Renaissance",
        "MMKK Musée art moderne Klagenfurt",
        "Minimundus parc miniatures Wörthersee",
        "Dragon fontaine Klagenfurt Lindwurmbrunnen",
        "Landeszeughaus armurerie Klagenfurt",
        "Wörthersee Klagenfurt promenade",
        "Wildensteiner Wasserfall cascade Carinthie sud",
        "cascade Wildenstein plateforme panoramique",
        "Rosen am Klopeiner See Wildenstein",
        "Klagenfurt centre historique Carinthie",
        "Alter Platz Klagenfurt nuit retour",
        "Aéroport Klagenfurt KLU"
      ],
      "rating": 6.8,
      "place_type": "large_city",
      "suggested_days": 1
    },
    {
      "place_id": "AT::klopeiner-see",
      "name": "Klopeiner See",
      "cc": "AT",
      "language": "fr",
      "coords": [
        46.6,
        14.5833
      ],
      "lat": 46.6,
      "lon": 14.5833,
      "visits": [
        {
          "text": "Le Klopeiner See est le lac le plus chaud d'Europe centrale : ses eaux atteignent 29°C en été, grâce à sa faible profondeur (maximum 14 m) et son exposition au soleil. Ce lac de 1,8 km de long aux eaux turquoise est entouré de collines boisées et dispose de plages et d'installations bien équipées sur tout son pourtour.",
          "visit_duration_min": 90
        },
        {
          "text": "La montée au sommet du Kitzelberg, sur la rive ouest, recompense après 45 minutes de sentier rocailleux par un panorama à 360° sur les eaux turquoise du lac et les montagnes carinthiennes environnantes. C'est le meilleur point de vue sur le lac.",
          "visit_duration_min": 60
        }
      ],
      "activities": [
        {
          "text": "Baignade, kayak, paddle et planche à voile depuis les plages aménagées du Klopeiner See. Les loueurs de matériel nautique sont présents sur les deux rives principales. Les sentiers cyclables autour du lac permettent d'en faire le tour en deux heures."
        }
      ],
      "days_plan": [
        {
          "itin_id": "AT::carinthia::lakes-mountains-alpine-roads",
          "itin_title": "Circuit Carinthie Autriche : Lacs, Routes Alpines et Châteaux",
          "day": 5
        }
      ],
      "map_keywords": [
        "Klopeiner See lac chaud Carinthie",
        "Kitzelberg point de vue Klopeiner See",
        "Klopein plage baignade",
        "lacs du sud Carinthie baignade"
      ],
      "rating": 4.2,
      "place_type": "nature",
      "suggested_days": 0.5
    },
    {
      "place_id": "AT::kreuzeck",
      "name": "Kreuzeck",
      "cc": "AT",
      "language": "fr",
      "coords": [
        46.8167,
        13.1
      ],
      "lat": 46.8167,
      "lon": 13.1,
      "visits": [
        {
          "text": "Le Kreuzeckbahn est l'un des derniers chemins de fer à crémaillère d'Autriche, partant de Spittal an der Drau pour grimper en quelques minutes jusqu'aux pâturages d'altitude du massif de Kreuzeck. Ce chemin de fer historique offre un voyage nostalgique à travers des paysages alpins spectaculaires, accessible à tous sans équipement particulier.",
          "visit_duration_min": 60
        },
        {
          "text": "Spittal an der Drau, à la base du téléphérique, possède l'un des plus beaux palais Renaissance d'Autriche : le Schloss Porcia (XVIe siècle), avec sa cour intérieure à trois galeries d'arcades superposées. Le musée de district qu'il abrite retrace l'histoire de la Haute Carinthie.",
          "visit_duration_min": 60
        }
      ],
      "activities": [
        {
          "text": "Randonnée familiale depuis la station supérieure du Kreuzeckbahn sur les sentiers balisés entre alpages et forêts. Les vues portent sur les lacs Millstätter See et Weissensee en contrebas. Le Kreuzeckbahn est inclus dans la Kärnten Card."
        }
      ],
      "days_plan": [
        {
          "itin_id": "AT::carinthia::lakes-mountains-alpine-roads",
          "itin_title": "Circuit Carinthie Autriche : Lacs, Routes Alpines et Châteaux",
          "day": 15
        }
      ],
      "map_keywords": [
        "Kreuzeckbahn chemin de fer crémaillère Spittal",
        "Kreuzeck randonnée panorama Carinthie",
        "Spittal an der Drau vieille ville"
      ],
      "rating": 3,
      "place_type": "nature",
      "suggested_days": 0.5
    },
    {
      "place_id": "AT::lech-am-arlberg",
      "name": "Lech Am Arlberg",
      "cc": "AT",
      "language": "fr",
      "coords": [
        47.2073,
        10.1411
      ],
      "lat": 47.2073,
      "lon": 10.1411,
      "visits": [
        {
          "text": "Village de Lech am Arlberg à 1 450 m, fondé au XIIIe siècle par des bergers walsers venus du Valais suisse. Leurs maisons traditionnelles en bois aux toits abrupts caractérisent encore le village élu plus beau village d'Europe en 2004. Le torrent Lech traverse le centre sous des ponts en pierre.",
          "visit_duration_min": 60
        },
        {
          "text": "Formarinsee (1 789 m), lac en forme de coeur élu plus bel endroit d'Autriche en 2015 par les lecteurs du magazine Heute. Eaux turquoise entourées de prairies alpines et de sommets à 2 500 m. Accessible par randonnée depuis Lech (2h, 350 m de dénivelé) ou en téléphérique jusqu'à Rüfikopf puis 45 min à pied.",
          "visit_duration_min": 150
        },
        {
          "text": "Téléphérique Rüfikopf (2 362 m) offrant un panorama à 360° sur le massif de l'Arlberg, les Alpes du Vorarlberg et, par temps clair, le massif du Säntis en Suisse. Restaurant d'altitude avec terrasse, point de départ de nombreuses randonnées vers les zones protégées.",
          "visit_duration_min": 90
        }
      ],
      "activities": [
        {
          "text": "Randonnée sur l'Arlberg Trail (40 km reliant Lech, Zürs, Stuben, St. Christoph et St. Anton) - même une journée sur le tronçon Lech-Zürs (8 km, 2h) offre des panoramas exceptionnels sur les alpages et les glaciers. Balisage rouge-blanc, niveau intermédiaire."
        },
        {
          "text": "Skyspace Lech, installation d'art contemporain de James Turrell intégrée dans le paysage. Cet espace de contemplation joue sur la perception de la lumière naturelle et du ciel à travers une ouverture zénithale. Visites guidées de 45 min en soirée pour les effets crépusculaires."
        }
      ],
      "days_plan": [
        {
          "itin_id": "AT::autriche::two-weeks-explorers",
          "itin_title": "Autriche en trois semaines : Wachau, Alpes et Salzbourg",
          "day": 10
        }
      ],
      "rating": 7.7,
      "place_type": "village",
      "suggested_days": 0.5
    },
    {
      "place_id": "AT::lechtal",
      "name": "Lechtal",
      "cc": "AT",
      "language": "fr",
      "coords": [
        47.272,
        10.338
      ],
      "lat": 47.272,
      "lon": 10.338,
      "visits": [
        {
          "text": "Découverte du pont suspendu de Holzgau au-dessus des gorges de Höhenbach",
          "visit_duration_min": 75
        },
        {
          "text": "Visite des villages typiques de la vallée du Lechtal",
          "visit_duration_min": 75
        }
      ],
      "activities": [
        {
          "text": "Balade dans la vallée du Tannheim et autour du lac d’Haldensee"
        }
      ],
      "days_plan": [
        {
          "itin_id": "AT::autriche::roadtrip-famille-nature-et-culture",
          "itin_title": "Road Trip Autriche : Nature, Culture et Lacs Alpins",
          "day": 8
        }
      ],
      "rating": 6.6,
      "place_type": "nature",
      "suggested_days": 1
    },
    {
      "place_id": "AT::malta-hochalmstrasse",
      "name": "Malta Hochalmstrasse",
      "cc": "AT",
      "language": "fr",
      "coords": [
        47.05,
        13.3333
      ],
      "lat": 47.05,
      "lon": 13.3333,
      "visits": [
        {
          "text": "La Malta Hochalmstrasse est l'une des plus belles routes panoramiques de Carinthie sur 14,4 km. La route longe une succession de barrages hydroélectriques encaissés entre des parois verticales, avec des cascades s'écoulant depuis les glaciers supérieurs. Des feux de circulation régulent le trafic dans les sections les plus étroites.",
          "visit_duration_min": 75
        },
        {
          "text": "Au terminus de la route, le barrage de Kölbrein est le plus haut barrage d'Autriche (200 m de hauteur). Une plateforme d'observation vitrée en porte-à-faux sur le vide donne une vue vertigineuse sur le bassin inférieur. La randonnée jusqu'au refuge Osnabrücker Hütte (2h30 aller) traverse une haute vallée suspendue avec cascades et éboulis.",
          "visit_duration_min": 90
        }
      ],
      "activities": [
        {
          "text": "La route est à péage (6 € par personne, gratuite avec la Kärnten Card). Ouverte de mai à fin octobre. La montée jusqu'au barrage peut être remplacée par la randonnée en sentier parallèle pour les amateurs de marche."
        }
      ],
      "days_plan": [
        {
          "itin_id": "AT::carinthia::lakes-mountains-alpine-roads",
          "itin_title": "Circuit Carinthie Autriche : Lacs, Routes Alpines et Châteaux",
          "day": 19
        }
      ],
      "map_keywords": [
        "Malta Hochalmstrasse route barrages Carinthie",
        "Barrage Kölbrein plus haut Autriche",
        "Osnabrücker Hütte refuge Malta",
        "cascades Malta Hochalmstrasse"
      ],
      "rating": 2.4,
      "place_type": "site",
      "suggested_days": 0.3
    },
    {
      "place_id": "AT::mayrhofen",
      "name": "Mayrhofen",
      "cc": "AT",
      "language": "fr",
      "coords": [
        47.1683,
        11.8643
      ],
      "lat": 47.1683,
      "lon": 11.8643,
      "visits": [
        {
          "text": "Village de Mayrhofen au fond du Zillertal, entouré des massifs du Penken (1 790 m) et de l'Ahorn (2 000 m). Ce village tyrolien aux chalets fleuris est le point de départ d'accès à quatre domaines montagneux. La rue principale Hauptstraße concentre boutiques d'équipement, restaurants et Heuriger (tavernes à vin).",
          "visit_duration_min": 45
        },
        {
          "text": "Penkenbahn, téléphérique 3S moderne (2015) reliant le village à la station d'Ahorn (2 000 m) en 10 minutes. Cabines de 32 personnes, 1 000 m de dénivelé, 3 km de ligne. Au sommet : panorama sur le Zillertal, les glaciers du Hintertux et les sommets des Alpes de Zillertal culminant à 3 510 m.",
          "visit_duration_min": 120
        },
        {
          "text": "Stilluptal, vallée sauvage au départ de Mayrhofen par une route à péage (5 €). Réserve naturelle protégée avec le réservoir Stillupstausee (80 millions de m³), des cascades et des sentiers forestiers. Parfaite pour une randonnée douce en forêt avec vue sur le barrage.",
          "visit_duration_min": 120
        },
        {
          "text": "Excursion à Hintertux et son glacier permanent (3 250 m), le seul glacier skiable en Autriche toute l'année. En été, on peut marcher sur la glace, explorer les crevasses balisées et profiter du panorama sur les Alpes de Zillertal depuis les 3 250 m. Téléphérique depuis le fond du Tuxertal.",
          "visit_duration_min": 180
        },
        {
          "text": "Grotte glaciaire de Hintertux (Gletschereis- und Tropfsteinhöhle), accessible à côté du téléphérique. Stalactites de glace et stalagmites dans un réseau de galeries creusées dans le glacier. Température -2°C, visite guidée de 45 minutes, éclairage spectaculaire.",
          "visit_duration_min": 60
        }
      ],
      "activities": [
        {
          "text": "Circuit panoramique Penken (4,4 km) depuis la station amont, sentier adapté aux poussettes et aux familles contournant les prairies alpines avec vues sur les quatre vallées du Zillertal. Durée 1h30, dénivelé minimal, plusieurs refuges jalonnent le parcours."
        },
        {
          "text": "Mine d'or de Zell am Ziller à 10 minutes en voiture - visite des galeries souterrains d'une ancienne mine d'or du XVIe siècle. Parcours en petit train minier suivi d'une exposition sur l'histoire de l'extraction. Ouvert mai-octobre."
        },
        {
          "text": "Randonnée au Schlegeisspeicher (1 782 m), réservoir alpin au fond du Zillertal Grund accessible par une route pittoresque depuis Ginzling (20 km depuis Mayrhofen). Lac turquoise entouré de sommets à plus de 3 000 m, sentiers faciles autour du lac. Parking à 8 €."
        },
        {
          "text": "Erlebnisbad Mayrhofen, complexe aquatique avec piscine couverte, toboggans, espace bien-être et piscine extérieure chauffée avec vue sur les montagnes. Idéal en cas de météo incertaine ou pour une soirée de détente après randonnée."
        }
      ],
      "days_plan": [
        {
          "itin_id": "AT::autriche::two-weeks-explorers",
          "itin_title": "Autriche en trois semaines : Wachau, Alpes et Salzbourg",
          "day": 6
        },
        {
          "itin_id": "AT::autriche::two-weeks-explorers",
          "itin_title": "Autriche en trois semaines : Wachau, Alpes et Salzbourg",
          "day": 7
        }
      ],
      "rating": 7.8,
      "place_type": "small_city",
      "suggested_days": 1
    },
    {
      "place_id": "AT::melk",
      "name": "Melk",
      "cc": "AT",
      "language": "fr",
      "coords": [
        48.2276,
        15.3313
      ],
      "lat": 48.2276,
      "lon": 15.3313,
      "visits": [
        {
          "text": "Perchée sur un éperon rocheux qui plonge directement dans le Danube, l'abbaye bénédictine de Melk est l'un des chefs-d'oeuvre du baroque européen. Construite entre 1702 et 1736 par Jakob Prandtauer, sa façade ocre et ses dômes dorés se voient de plusieurs kilomètres. Depuis 1089 - soit plus de 930 ans - des moines bénédictins y vivent sans interruption selon la règle de saint Benoît. La bibliothèque aux 100 000 volumes, avec son plafond peint par Paul Troger, compte parmi les plus belles bibliothèques baroques du monde. L'église abbatiale, les appartements impériaux et les jardins aux tilleuls tricentenaires complètent une visite d'une heure et demie à deux heures.",
          "visit_duration_min": 120
        },
        {
          "text": "Dürnstein, petit village de 870 habitants sur la rive du Danube, est célèbre pour deux raisons : son clocher baroque bleu cobalt - surnommé « le doigt de Dieu » - qui signale les bateaux depuis le XVIIIe siècle, et les ruines du château médiéval perché au-dessus du village où Richard Coeur de Lion fut emprisonné par Léopold V d'Autriche en 1192-1193 après la croisade. La montée aux ruines (30 à 45 minutes) récompense par une vue exceptionnelle sur la boucle du Danube et les vignobles de la Wachau.",
          "visit_duration_min": 90
        },
        {
          "text": "La vallée de la Wachau, classée au patrimoine mondial de l'UNESCO depuis 2000, est une bande de 30 km entre Krems et Melk où le Danube serpente entre terrasses de vignobles et villages médiévaux. Le Grüner Veltliner et le Riesling de Wachau figurent parmi les vins blancs les plus réputés d'Autriche. Chaque village cache ses propres cours intérieures, ruelles pavées et ruines de fortifications.",
          "visit_duration_min": 60
        }
      ],
      "activities": [
        {
          "text": "Croisière fluviale courte sur le Danube dans la Wachau. Les bateaux naviguent entre les villages de vignerons, passent sous les ruines de Dürnstein, longent les terrasses d'abricotiers et les vergers qui font la réputation gastronomique de la région. L'abricot de Wachau, protégé par une appellation contrôlée européenne, est transformé en schnaps, confitures et quenelles traditionnelles."
        },
        {
          "text": "Balade à vélo sur la piste cyclable du Danube (Donauradweg) qui longe les deux rives du fleuve dans la Wachau. Le parcours plat et bien entretenu traverse vignobles, vergers et villages historiques à un rythme paisible. Les loueurs de vélos sont disponibles à Melk et Krems."
        }
      ],
      "days_plan": [
        {
          "itin_id": "AT::austria-family-roadtrip",
          "itin_title": "Voyage Autriche en Famille : Montagnes, Lacs et Palais Impériaux",
          "day": 6
        }
      ],
      "map_keywords": [
        "Abbaye de Melk Danube baroque",
        "Vallée Wachau Danube vignobles",
        "Dürnstein clocher bleu Wachau",
        "Krems-an-der-Donau vieille ville",
        "Spitz an der Donau",
        "Göttweig abbaye Wachau"
      ],
      "rating": 5.2,
      "place_type": "small_city",
      "suggested_days": 0.5
    },
    {
      "place_id": "AT::millstattersee",
      "name": "Millstattersee",
      "cc": "AT",
      "language": "fr",
      "coords": [
        46.8,
        13.5833
      ],
      "lat": 46.8,
      "lon": 13.5833,
      "visits": [
        {
          "text": "Le Millstätter See (11,5 km de long, 141 m de profondeur) est le deuxième plus grand lac de Carinthie et l'un des plus préservés. Entouré de montagnes dépassant 2 000 m et de forêts de sapins et de hêtres se reflétant dans une eau cristalline, il alimente en eau potable les communautés locales sans traitement - indicateur de sa pureté exceptionnelle.",
          "visit_duration_min": 60
        },
        {
          "text": "L'abbaye bénédictine de Millstatt, fondée en 1070, est l'un des plus importants ensembles monastiques romans d'Autriche. Le cloître du XIIe siècle présente des chapiteaux sculptés représentant des scènes bibliques et mythologiques uniques. La bibliothèque conserve plus de 30 000 volumes dont des manuscrits enluminés médiévaux. Chaque été, l'église abbatiale accueille les Concerts Internationaux de Millstatt.",
          "visit_duration_min": 90
        }
      ],
      "activities": [
        {
          "text": "Montée en téléphérique au Goldeck (2 142 m) pour des randonnées avec vues panoramiques sur le lac depuis les crêtes. La Goldeck Panoramastrasse offre une alternative en voiture jusqu'à 1 900 m. Baignade sur les plages du lac en fin de journée."
        }
      ],
      "days_plan": [
        {
          "itin_id": "AT::carinthia::lakes-mountains-alpine-roads",
          "itin_title": "Circuit Carinthie Autriche : Lacs, Routes Alpines et Châteaux",
          "day": 20
        }
      ],
      "map_keywords": [
        "Millstätter See lac Carinthie",
        "Abbaye Millstatt bénédictins romane",
        "Goldeck téléphérique panorama Millstatt",
        "concerts internationaux Millstatt abbaye"
      ],
      "rating": 4.7,
      "place_type": "nature",
      "suggested_days": 0.5
    },
    {
      "place_id": "AT::molltal-glacier",
      "name": "Molltal Glacier",
      "cc": "AT",
      "language": "fr",
      "coords": [
        47.0167,
        13.0167
      ],
      "lat": 47.0167,
      "lon": 13.0167,
      "visits": [
        {
          "text": "Le glacier du Mölltal, à 3 122 m d'altitude à la frontière Carinthie-Salzbourg, est accessible par une combinaison unique : un téléphérique souterrain (Glacier Express) creusé dans la montagne, suivi d'un second téléphérique. Autour du glacier, des lacs d'un turquoise intense contrastent avec les parois rocheuses grises et la glace bleue.",
          "visit_duration_min": 90
        }
      ],
      "activities": [
        {
          "text": "Randonnée glaciaire guidée en été sur les sentiers balisés autour du glacier. Les vues sur les sommets des Hohe Tauern depuis 3 000 m sont parmi les plus spectaculaires accessibles sans alpinisme. Le téléphérique est inclus dans la Kärnten Card."
        }
      ],
      "days_plan": [
        {
          "itin_id": "AT::carinthia::lakes-mountains-alpine-roads",
          "itin_title": "Circuit Carinthie Autriche : Lacs, Routes Alpines et Châteaux",
          "day": 17
        }
      ],
      "map_keywords": [
        "Glacier Mölltal téléphérique souterrain Carinthie",
        "Mölltal Gletscher 3122m",
        "lacs glaciaires turquoise Mölltal",
        "Flattach Mölltal accès glacier"
      ],
      "rating": 9.2,
      "place_type": "nature",
      "suggested_days": 0.5
    },
    {
      "place_id": "AT::nassfeld",
      "name": "Nassfeld",
      "cc": "AT",
      "language": "fr",
      "coords": [
        46.5583,
        13.2833
      ],
      "lat": 46.5583,
      "lon": 13.2833,
      "visits": [
        {
          "text": "Nassfeld-Pressegger See est une région de montagne à la frontière austro-italienne, paradis des sports de plein air en toutes saisons. Le Pressegger See, lac thermal naturel à 560 m d'altitude, propose une baignade dans des eaux plus chaudes que la plupart des lacs alpins. En hiver, Nassfeld est l'une des plus grandes stations de ski de Carinthie avec 110 km de pistes.",
          "visit_duration_min": 75
        },
        {
          "text": "La montée au Gartnerkofel (2 195 m) en téléphérique puis à pied ouvre sur un panorama frontalier exceptionnel : d'un côté la Carinthie et ses lacs, de l'autre les Dolomites frioulanes italiennes. Par temps clair, la vue porte jusqu'à l'Adriatique.",
          "visit_duration_min": 75
        }
      ],
      "activities": [
        {
          "text": "Randonnée ou VTT sur les sentiers balisés du massif de Nassfeld. Les itinéraires balisés vont de promenades familiales en fond de vallée aux randonnées de crête exigeantes. Les pistes VTT de descente depuis le Gartnerkofel sont parmi les plus techniques de Carinthie."
        }
      ],
      "days_plan": [
        {
          "itin_id": "AT::carinthia::lakes-mountains-alpine-roads",
          "itin_title": "Circuit Carinthie Autriche : Lacs, Routes Alpines et Châteaux",
          "day": 12
        }
      ],
      "map_keywords": [
        "Nassfeld Pressegger See Carinthie Italie",
        "Gartnerkofel sommet Nassfeld",
        "Nassfeld station ski été randonnée",
        "Pressegger See lac Nassfeld"
      ],
      "rating": 5.8,
      "place_type": "nature",
      "suggested_days": 0.5
    },
    {
      "place_id": "AT::oetztal",
      "name": "Oetztal",
      "cc": "AT",
      "language": "fr",
      "coords": [
        47.128,
        10.963
      ],
      "lat": 47.128,
      "lon": 10.963,
      "visits": [
        {
          "text": "Visite de la vallée de l’Ötztal et ascension vers la cascade de Stuibenfall",
          "visit_duration_min": 75
        }
      ],
      "activities": [
        {
          "text": "Randonnée sur les escaliers panoramiques dominant la chute d’eau"
        }
      ],
      "days_plan": [
        {
          "itin_id": "AT::autriche::roadtrip-famille-nature-et-culture",
          "itin_title": "Road Trip Autriche : Nature, Culture et Lacs Alpins",
          "day": 6
        }
      ],
      "rating": 5.3,
      "place_type": "nature",
      "suggested_days": 1
    },
    {
      "place_id": "AT::pertisau-achensee",
      "name": "Pertisau Achensee",
      "cc": "AT",
      "language": "fr",
      "coords": [
        47.4326,
        11.7389
      ],
      "lat": 47.4326,
      "lon": 11.7389,
      "visits": [
        {
          "text": "Lac Achensee, le plus grand lac du Tyrol (9 km de long, 1,5 km de large) à 930 m d'altitude entre les massifs du Karwendel et du Rofan. L'eau d'une clarté exceptionnelle (visibilité jusqu'à 10 m) et ses teintes turquoise changeantes selon la lumière en font l'un des plus beaux lacs des Alpes autrichiennes.",
          "visit_duration_min": 60
        },
        {
          "text": "Village de Pertisau sur la rive ouest du lac, préservé avec son architecture alpine traditionnelle. Centre du lac et point de départ de toutes les activités : navigation, randonnées vers le Karwendel, via ferratas. L'église baroque du XVIIIe siècle mérite un coup d'oeil.",
          "visit_duration_min": 45
        },
        {
          "text": "Navigation en bateau sur l'Achensee avec la compagnie Achenseeschifffahrt (130 ans d'histoire, 6 embarcadères). Le MS Stella Maris (1912) fut le premier bateau à moteur diesel d'Autriche. Traversée complète Pertisau-Achenkirch en 40 minutes, arrêt possible à la Gaisalm accessible uniquement par bateau ou à pied.",
          "visit_duration_min": 90
        }
      ],
      "activities": [
        {
          "text": "Randonnée Gaisalm depuis Pertisau (8,8 km, 2h) le long de la rive est sauvage sans route carrossable. Refuge isolé de la Gaisalm accessible uniquement par ce sentier ou en bateau. Retour en bateau possible. Niveau intermédiaire, sentier bien balisé."
        },
        {
          "text": "Chemin de fer à vapeur de l'Achensee (Achenseebahn, 1889), voie étroite de 6,79 km reliant Jenbach à l'Achensee avec 440 m de dénivelé positif. La locomotive à vapeur originale est la plus ancienne d'Autriche encore en service. Départs depuis Jenbach (15 min en voiture de Pertisau) d'avril à octobre."
        }
      ],
      "days_plan": [
        {
          "itin_id": "AT::autriche::two-weeks-explorers",
          "itin_title": "Autriche en trois semaines : Wachau, Alpes et Salzbourg",
          "day": 8
        }
      ],
      "rating": 5.7,
      "place_type": "village",
      "suggested_days": 0.5
    },
    {
      "place_id": "AT::salzburg",
      "name": "Salzburg",
      "cc": "AT",
      "language": "fr",
      "coords": [
        47.80949,
        13.05501
      ],
      "lat": 47.80949,
      "lon": 13.05501,
      "visits": [
        {
          "text": "Forteresse Hohensalzburg, l'une des mieux conservées d'Europe, dominant la ville depuis un éperon rocheux à 120 m. Construite en 1077 par l'archevêque Gebhard, agrandie jusqu'au XVIe siècle. Les appartements princiers, la salle d'armes et le panorama sur les Alpes salzbourgeoises depuis les remparts justifient la montée en funiculaire ou à pied.",
          "visit_duration_min": 120
        },
        {
          "text": "Vieille ville (Altstadt) de Salzbourg inscrite à l'UNESCO, ensemble baroque exceptionnel érigé sous les princes-archevêques du XVIIe siècle. La Getreidegasse avec ses enseignes en fer forgé, la Residenzplatz avec sa fontaine baroque, et les multiples galeries d'art et boutiques composent une scénographie urbaine unique.",
          "visit_duration_min": 90
        },
        {
          "text": "Cathédrale de Salzbourg (Dom), chef-d'oeuvre baroque d'Italie du Nord à trois nefs achevé en 1628. Les fresques de la coupole, les orgues monumentaux et les bronzes de la façade en font l'un des plus beaux édifices religieux des Alpes. Mozart y fut baptisé le 28 janvier 1756.",
          "visit_duration_min": 60
        },
        {
          "text": "Mirabellgarten, jardin à la française du XVIIe siècle conçu par Fischer von Erlach, avec la forteresse Hohensalzburg en toile de fond. Les parterres géométriques, les statues mythologiques, le bassin central et les fontaines offrent la composition photographique la plus célèbre de Salzbourg.",
          "visit_duration_min": 60
        },
        {
          "text": "Maison natale de Mozart (Mozarts Geburtshaus), Getreidegasse 9 - appartement du troisième étage où Wolfgang Amadeus naquit le 27 janvier 1756. Le clavecin d'enfant, le violon miniature et les partitions manuscrites originaux sont parmi les pièces les plus touchantes de ce musée biographique.",
          "visit_duration_min": 60
        },
        {
          "text": "Résidence des Princes-Archevêques (Residenz), palais baroque de 180 pièces occupant tout un côté de la Residenzplatz. La Galerie des Princes abrite une collection remarquable de Rembrandt, Rubens et peintures flamandes. La grande salle de réception avec ses fresques illusionnistes est l'un des espaces baroques les plus impressionnants d'Autriche.",
          "visit_duration_min": 75
        },
        {
          "text": "Hellbrunn, château de plaisance du XVIIe siècle à 4 km du centre avec son célèbre Wasserspiele (jeux d'eau mécaniques). L'archevêque Markus Sittikus fit installer 265 jets d'eau cachés pour surprendre ses invités lors des banquets. Toujours en état de marche, ces automates hydrauliques sont uniques en Europe.",
          "visit_duration_min": 120
        }
      ],
      "activities": [
        {
          "text": "Promenade sur le Mönchsberg, colline boisée accessible par ascenseur depuis la vieille ville (3 €). Vue aérienne sur l'ensemble de la ville et le château depuis la terrasse du Café Winkler. Musée d'Art Moderne (Museum der Moderne) au sommet avec collection contemporaine."
        },
        {
          "text": "Concert ou récital Mozart dans l'un des cadres historiques de Salzbourg : Mozarteum, Résidence ou Château Mirabell. Les concerts de chambre quotidiens en costume d'époque dans les salons du XVIIIe siècle sont une expérience authentique et non touristique."
        },
        {
          "text": "Tour des lacs salzbourgeois - excursion aux Salzkammergut proches (Saint-Wolfgang, Mondsee, Wolfgangsee) à 40-50 km de Salzbourg. Le Mondsee avec son église baroque (décor de La Mélodie du Bonheur) et Saint-Wolfgang avec son retable de Pacher (1481) sont accessibles en une demi-journée."
        },
        {
          "text": "Marché et gastronomie salzbourgeoise sur la Grünmarkt (marché quotidien) près de la cathédrale. Spécialités : Mozartkugeln authentiques de Fürst (pas la version en papier aluminium), pain paysan, fromages des alpages et Stiegl Goldbräu en pression dans les jardins de bière du Mönchsberg."
        }
      ],
      "days_plan": [
        {
          "itin_id": "AT::eastern-alps::lacs-et-montagnes-7j",
          "itin_title": "Road Trip Autriche : Vienne, Salzbourg, Tyrol et Lacs Alpins",
          "day": 5
        },
        {
          "itin_id": "AT::austria-family-roadtrip",
          "itin_title": "Voyage Autriche en Famille : Montagnes, Lacs et Palais Impériaux",
          "day": 7
        },
        {
          "itin_id": "AT::autriche::two-weeks-explorers",
          "itin_title": "Autriche en trois semaines : Wachau, Alpes et Salzbourg",
          "day": 14
        },
        {
          "itin_id": "AT::autriche::two-weeks-explorers",
          "itin_title": "Autriche en trois semaines : Wachau, Alpes et Salzbourg",
          "day": 15
        }
      ],
      "rating": 9.6,
      "place_type": "large_city",
      "suggested_days": 1.5
    },
    {
      "place_id": "AT::sankt-veit-an-der-glan",
      "name": "Sankt Veit An Der Glan",
      "cc": "AT",
      "language": "fr",
      "coords": [
        46.7733,
        14.3567
      ],
      "lat": 46.7733,
      "lon": 14.3567,
      "visits": [
        {
          "text": "Le château de Hochosterwitz est l'un des plus spectaculaires d'Autriche : une forteresse médiévale perchée sur un éperon rocheux calcaire de 160 mètres dominant la plaine carinthienne, visible à des dizaines de kilomètres à la ronde. Construit dès 860 et remanié au XVIe siècle par la famille Khevenhüller, il a conservé pratiquement la même apparence depuis. Son chemin d'accès hélicoïdal de 620 mètres franchit 14 portes fortifiées successives, chacune dotée de dispositifs défensifs différents - herses, mâchicoulis, ponts-levis - qui, selon la tradition, le rendirent imprenable pendant des siècles.",
          "visit_duration_min": 120
        },
        {
          "text": "Les salles intérieures ouvertes au public exposent collections d'armures, peintures et objets préhistoriques. La chapelle du château, construite en 1571, conserve ses fresques d'origine. Un ascenseur depuis le parking permet aux visiteurs à mobilité réduite d'accéder directement à l'entrée principale.",
          "visit_duration_min": 60
        }
      ],
      "activities": [
        {
          "text": "Baignade au lac Längsee, à quelques kilomètres du château. Ce petit lac propre et peu fréquenté offre une pause fraîche après la visite de la forteresse. Ses berges boisées et son eau claire en font une halte idéale pour les familles."
        }
      ],
      "days_plan": [
        {
          "itin_id": "AT::carinthia::lakes-mountains-alpine-roads",
          "itin_title": "Circuit Carinthie Autriche : Lacs, Routes Alpines et Châteaux",
          "day": 2
        }
      ],
      "map_keywords": [
        "Château Hochosterwitz 14 portes Carinthie",
        "Sankt Georgen am Längsee Carinthie",
        "Sankt Veit an der Glan centre historique",
        "Sankt Veit an der Glan Hauptplatz",
        "Längsee lac Carinthie"
      ],
      "rating": 9.4,
      "place_type": "small_city",
      "suggested_days": 0.5
    },
    {
      "place_id": "AT::st-wolfgang-im-salzkammergut",
      "name": "St Wolfgang Im Salzkammergut",
      "cc": "AT",
      "language": "fr",
      "coords": [
        47.738962,
        13.449651
      ],
      "lat": 47.738962,
      "lon": 13.449651,
      "visits": [
        {
          "text": "Wolfgangsee : promenade de rive et vues sur le Schafberg",
          "visit_duration_min": 75
        },
        {
          "text": "Mondsee : cloître et lac propice à la baignade estivale",
          "visit_duration_min": 75
        }
      ],
      "activities": [
        {
          "text": "Baignade au Wolfgangsee (eau jusqu’à 25°C en été)"
        },
        {
          "text": "Mini-croisière ou location de barque sur le Wolfgangsee"
        }
      ],
      "days_plan": [
        {
          "itin_id": "AT::eastern-alps::lacs-et-montagnes-7j",
          "itin_title": "Road Trip Autriche : Vienne, Salzbourg, Tyrol et Lacs Alpins",
          "day": 3
        }
      ],
      "rating": 5,
      "place_type": "small_city",
      "suggested_days": 0.5
    },
    {
      "place_id": "AT::vienna",
      "name": "Vienna",
      "cc": "AT",
      "language": "fr",
      "coords": [
        48.2082,
        16.3738
      ],
      "lat": 48.2082,
      "lon": 16.3738,
      "visits": [
        {
          "text": "Le palais de Schönbrunn, surnommé le « Versailles viennois », fut la résidence d'été des Habsbourg pendant des siècles. Ses 1 441 pièces ne sont pas toutes visitables, mais les appartements de François-Joseph et d'Élisabeth (Sissi), les salles d'apparat de Marie-Thérèse et les décors rococo à la chinoiserie constituent une immersion complète dans la vie de cour impériale. Le Musée des enfants permet aux plus petits de s'habiller en princes et princesses, et d'apprendre les jeux et les coutumes des enfants impériaux.",
          "visit_duration_min": 120
        },
        {
          "text": "Les jardins de Schönbrunn, ouverts gratuitement dès 6h30, s'étendent sur 1,2 km d'est en ouest. La Gloriette, colonnade triomphale au sommet de la colline, offre une vue panoramique sur Vienne. Le labyrinthe de haies taillées et les fontaines classées sont parfaits pour une promenade en famille.",
          "visit_duration_min": 60
        },
        {
          "text": "Le Musée Sisi (Hofburg) plonge dans la vie intime de l'impératrice Élisabeth à travers ses robes originales, ses lettres et ses portraits. Le Musée Sisi, situé dans la Hofburg, révèle la personnalité complexe et souvent mélancolique derrière la légende : ses régimes sévères, ses voyages incessants et sa relation difficile avec l'étiquette de la cour.",
          "visit_duration_min": 75
        },
        {
          "text": "La Haus der Musik (Maison de la Musique) est un musée interactif installé dans un palais du centre-ville. Chaque étage est dédié à un compositeur viennois - Haydn, Mozart, Beethoven, Schubert, Strauss, Mahler. Les enfants peuvent composer leur propre valse, diriger l'Orchestre philharmonique de Vienne virtuel ou entendre la musique à travers les battements de leur propre coeur.",
          "visit_duration_min": 90
        },
        {
          "text": "La cathédrale Saint-Étienne (Stephansdom), construite à partir de 1160 en pierre calcaire de la région, est le symbole de Vienne. Son toit de tuiles multicolores forme des motifs géométriques spectaculaires visibles depuis les toits de la vieille ville. Les catacombes sous la cathédrale abritent les ossements de 11 000 Viennois victoires des épidémies du XVIIe siècle.",
          "visit_duration_min": 60
        }
      ],
      "activities": [
        {
          "text": "Pique-nique et balade dans le Prater, immense parc populaire de Vienne sur les bords du Danube. Le Wurstelprater, parc d'attractions ouvert en 1766, abrite la Grande Roue (Riesenrad) construite en 1897, qui culmine à 65 mètres : une vue panoramique sur Vienne depuis ses wagons d'acier. Les 250 attractions - manèges, maisons hantées, montagnes russes - font le bonheur des familles."
        },
        {
          "text": "Le zoo de Schönbrunn (Tiergarten), fondé en 1752, est le plus ancien zoo du monde encore en activité. Plus de 700 espèces animales, dont des pandas géants, des éléphants d'Afrique et des rhinocéros blancs, occupent des enclos réaménagés en espaces naturels. Des programmes quotidiens permettent aux enfants d'observer les animaux de près lors des repas."
        }
      ],
      "days_plan": [
        {
          "itin_id": "AT::autriche::roadtrip-famille-nature-et-culture",
          "itin_title": "Road Trip Autriche : Nature, Culture et Lacs Alpins",
          "day": 1
        },
        {
          "itin_id": "AT::eastern-alps::lacs-et-montagnes-7j",
          "itin_title": "Road Trip Autriche : Vienne, Salzbourg, Tyrol et Lacs Alpins",
          "day": 1
        },
        {
          "itin_id": "AT::eastern-alps::lacs-et-montagnes-7j",
          "itin_title": "Road Trip Autriche : Vienne, Salzbourg, Tyrol et Lacs Alpins",
          "day": 2
        },
        {
          "itin_id": "AT::austria-family-roadtrip",
          "itin_title": "Voyage Autriche en Famille : Montagnes, Lacs et Palais Impériaux",
          "day": 5
        },
        {
          "itin_id": "AT::autriche::two-weeks-explorers",
          "itin_title": "Autriche en trois semaines : Wachau, Alpes et Salzbourg",
          "day": 1
        }
      ],
      "rating": 10,
      "place_type": "capital",
      "suggested_days": 3,
      "map_keywords": [
        "Palais Schönbrunn Vienne",
        "Hofburg Vienne Sissi",
        "Haus der Musik Vienne",
        "Stephansdom Vienne",
        "Belvédère Vienne",
        "Prater Grande Roue Vienne",
        "Zoo Tiergarten Schönbrunn"
      ]
    },
    {
      "place_id": "AT::villach",
      "name": "Villach",
      "cc": "AT",
      "language": "fr",
      "coords": [
        46.6111,
        13.8558
      ],
      "lat": 46.6111,
      "lon": 13.8558,
      "visits": [
        {
          "text": "Les chutes de Krimml (Krimmler Wasserfälle) plongent en trois cascades successives de 140, 100 et 140 mètres - 380 mètres au total - depuis un vallon suspendu à 1 470 mètres d'altitude. Ce sont les plus hautes chutes d'Europe et les cinquièmes du monde. Le sentier de randonnée de 4 km, bien entretenu avec des belvédères aménagés, permet d'atteindre la cascade inférieure en 15 minutes, la supérieure en une heure environ. La brume permanente de l'eau qui s'écrase sur la roche crée une atmosphère unique, et la végétation de mousses et de fougères géantes qui tapisse les berges renforce l'impression d'entrer dans un monde à part.",
          "visit_duration_min": 120
        },
        {
          "text": "Le parc national du Hohe Tauern, avec ses 1 856 km² de wilderness alpine, abrite le Grossglockner (3 798 m), plus haut sommet d'Autriche, des glaciers, des bouquetins, des marmottes et des aigles royaux. Le centre des visiteurs de Mittersill propose des expositions interactives sur la faune et la flore protégées. Des rangers organisent des sorties guidées pour découvrir l'écosystème alpin.",
          "visit_duration_min": 60
        },
        {
          "text": "Le lac Wörthersee, à deux pas de Villach, est l'un des lacs alpins les plus chauds d'Europe - ses eaux atteignent 28°C en été grâce à des sources thermales sous-lacustres. Ses rives sont équipées de promenades et de plages, et les villages de Pörtschach et Velden offrent un cadre Belle Époque avec leurs villas et leurs hôtels centenaires.",
          "visit_duration_min": 75
        }
      ],
      "activities": [
        {
          "text": "Baignade et paddle en famille sur le lac Wörthersee. Les loueurs proposent pédalos, kayaks et planches à pagaie sur les plages aménagées de Pörtschach et Maria Wörth. Pour les enfants, les zones de baignade surveillées avec fonds peu profonds sont sécurisées."
        },
        {
          "text": "⚠️ Note logistique : Les chutes de Krimml se trouvent à 120 km de Villach. La journée J3 est très chargée : il est recommandé de partir tôt le matin pour les chutes, de prévoir un pique-nique sur place, et de rejoindre Villach et ses lacs en fin d'après-midi. Envisagez de passer la nuit au Salzburgerland (Zell am See ou Mittersill) pour une logistique plus équilibrée."
        }
      ],
      "days_plan": [
        {
          "itin_id": "AT::carinthia::lakes-mountains-alpine-roads",
          "itin_title": "Circuit Carinthie Autriche : Lacs, Routes Alpines et Châteaux",
          "day": 8
        },
        {
          "itin_id": "AT::austria-family-roadtrip",
          "itin_title": "Voyage Autriche en Famille : Montagnes, Lacs et Palais Impériaux",
          "day": 3
        }
      ],
      "rating": 8.6,
      "place_type": "city",
      "suggested_days": 0.5,
      "map_keywords": [
        "Chutes de Krimml Hohe Tauern",
        "Grossglockner Route alpine",
        "Lac Wörthersee Carinthie",
        "Lac Faaker See Villach",
        "Villach vieille ville",
        "Lac Millstätter See Carinthie"
      ]
    },
    {
      "place_id": "AT::wachau",
      "name": "Wachau",
      "cc": "AT",
      "language": "fr",
      "coords": [
        48.38,
        15.43
      ],
      "lat": 48.38,
      "lon": 15.43,
      "visits": [
        {
          "text": "Exploration de la vallée de la Wachau et de ses vignobles",
          "visit_duration_min": 75
        },
        {
          "text": "Visite de l’abbaye de Melk et du château d’Aggstein",
          "visit_duration_min": 75
        },
        {
          "text": "Découverte du village de Dürnstein et de l’abbaye de Göttweig",
          "visit_duration_min": 75
        }
      ],
      "activities": [
        {
          "text": "Balade à vélo ou en bateau sur le Danube"
        }
      ],
      "days_plan": [
        {
          "itin_id": "AT::autriche::roadtrip-famille-nature-et-culture",
          "itin_title": "Road Trip Autriche : Nature, Culture et Lacs Alpins",
          "day": 2
        }
      ],
      "rating": 8,
      "place_type": "nature",
      "suggested_days": 1
    },
    {
      "place_id": "AT::weissensee",
      "name": "Weissensee",
      "cc": "AT",
      "language": "fr",
      "coords": [
        46.7167,
        13.3
      ],
      "lat": 46.7167,
      "lon": 13.3,
      "visits": [
        {
          "text": "Le Weissensee est le lac naturel le plus élevé (930 m) et le plus préservé de Carinthie, dans les Alpes Carniques. Long de 11,6 km, seulement un tiers de ses rives est accessible - le reste demeure totalement sauvage et protégé. La qualité de l'eau est exceptionnelle, avec une visibilité sous-marine atteignant 10 mètres en été, ce qui en fait un des lacs les plus clairs d'Europe.",
          "visit_duration_min": 60
        },
        {
          "text": "En hiver, le Weissensee se transforme en l'une des plus grandes patinoires naturelles d'Europe avec 6,2 km² de surface glacée. La glace naturelle atteint 40 à 50 cm d'épaisseur et accueille chaque année le marathon de patinage de Weissensee, l'un des plus anciens et des plus courus d'Europe.",
          "visit_duration_min": 45
        }
      ],
      "activities": [
        {
          "text": "Baignade, kayak et randonnée sur la rive est, plus sauvage et tranquille. La rive ouest, autour du village de Techendorf, regroupe les hôtels et les plages aménagées. Le tour du lac à pied ou à vélo est une excursion de demi-journée qui révèle les contrastes entre les deux rives."
        },
        {
          "text": "Randonnée vers le Granattor depuis Techendorf - sentier balisé de 3h offrant des vues plongeantes sur l'ensemble du lac depuis les crêtes des Alpes Carniques."
        }
      ],
      "days_plan": [
        {
          "itin_id": "AT::carinthia::lakes-mountains-alpine-roads",
          "itin_title": "Circuit Carinthie Autriche : Lacs, Routes Alpines et Châteaux",
          "day": 14
        }
      ],
      "map_keywords": [
        "Weissensee lac naturel Alpes Carniques",
        "Weissensee patinoire naturelle hiver",
        "Weissensee marathon patinage",
        "Techendorf Weissensee village"
      ],
      "rating": 4.8,
      "place_type": "nature",
      "suggested_days": 0.5
    },
    {
      "place_id": "AT::wolayersee",
      "name": "Wolayersee",
      "cc": "AT",
      "language": "fr",
      "coords": [
        46.6167,
        12.8833
      ],
      "lat": 46.6167,
      "lon": 12.8833,
      "visits": [
        {
          "text": "Le Wolayersee est l'un des plus beaux lacs de montagne de Carinthie, perché en altitude à la frontière austro-italienne dans les Alpes Carniques. Le lac est accessible après une randonnée de 3 heures depuis la chapelle Hubertuskapelle (point de départ avec parking). L'eau d'un bleu-vert limpide, les prairies alpines et les sommets qui l'encadrent composent un tableau d'une beauté saisissante. Un refuge au bord du lac propose restauration et hébergement.",
          "visit_duration_min": 90
        },
        {
          "text": "La chapelle Hubertuskapelle, au départ du sentier, vaut l'arrêt avant de commencer l'ascension. Cette petite chapelle alpine du XVIIIe siècle est un lieu de pèlerinage traditionnel pour les chasseurs et les bergers de la région.",
          "visit_duration_min": 30
        }
      ],
      "activities": [
        {
          "text": "Randonnée aller-retour Hubertuskapelle - Wolayersee : 3h à l'aller, 2h30 au retour, dénivelé modéré. Arriver tôt pour le stationnement (parking limité). Pique-nique ou repas au refuge du lac. Prévoir chaussures de randonnée et vêtements chauds - le lac est à plus de 1 800 m."
        }
      ],
      "days_plan": [
        {
          "itin_id": "AT::carinthia::lakes-mountains-alpine-roads",
          "itin_title": "Circuit Carinthie Autriche : Lacs, Routes Alpines et Châteaux",
          "day": 13
        }
      ],
      "map_keywords": [
        "Wolayersee lac alpin frontière Italie Carinthie",
        "Hubertuskapelle chapelle Wolayersee",
        "refuge Wolayersee randonnée",
        "Alpes Carniques Wolayersee randonnée"
      ],
      "rating": 3.6,
      "place_type": "nature",
      "suggested_days": 0.3
    },
    {
      "place_id": "AT::worthersee",
      "name": "Worthersee",
      "cc": "AT",
      "language": "fr",
      "coords": [
        46.6283,
        14.1458
      ],
      "lat": 46.6283,
      "lon": 14.1458,
      "visits": [
        {
          "text": "Le Wörthersee, 19,4 km de long, est le lac le plus célèbre de Carinthie et l'une des destinations balnéaires les plus exclusives d'Autriche. Ses eaux atteignent 28°C en été grâce à sa situation abritée. Depuis la Belle Époque, l'aristocratie austro-hongroise construisait de somptueuses villas Art nouveau sur ses rives - Brahms y composa sa deuxième symphonie à Pörtschach en 1877.",
          "visit_duration_min": 60
        },
        {
          "text": "Le Pyramidenkogel, inauguré en 2013, est la plus haute tour d'observation en bois du monde avec ses 100 mètres de hauteur. Un ascenseur atteint la plateforme panoramique en 30 secondes : vue à 360° sur l'ensemble du Wörthersee, les lacs voisins et les Alpes carinthiennes. La descente par le toboggan en spirale de 120 mètres est une attraction en soi.",
          "visit_duration_min": 75
        },
        {
          "text": "Velden am Wörthersee, surnommée le « Monte-Carlo autrichien », possède son casino historique et le Grand Hotel Schloss Velden (1590, reconverti en palace). Son élégante promenade au bord de l'eau et ses terrasses animent les soirées carinthiennes.",
          "visit_duration_min": 60
        }
      ],
      "activities": [
        {
          "text": "Baignade sur les plages de Pörtschach ou Maria Wörth. La presqu'île de Maria Wörth, avec son église du Xe siècle reflétée dans le lac, est l'image iconique du Wörthersee. Les plages publiques sont accessibles gratuitement."
        }
      ],
      "days_plan": [
        {
          "itin_id": "AT::carinthia::lakes-mountains-alpine-roads",
          "itin_title": "Circuit Carinthie Autriche : Lacs, Routes Alpines et Châteaux",
          "day": 6
        }
      ],
      "map_keywords": [
        "Wörthersee lac Carinthie Velden",
        "Pyramidenkogel tour bois panorama",
        "Pörtschach Wörthersee plage",
        "Velden casino Grand Hotel",
        "Maria Wörth église presqu'île"
      ],
      "rating": 5.6,
      "place_type": "nature",
      "suggested_days": 0.5
    },
    {
      "place_id": "AT::zell-am-see",
      "name": "Zell Am See",
      "cc": "AT",
      "language": "fr",
      "coords": [
        47.323,
        12.796
      ],
      "lat": 47.323,
      "lon": 12.796,
      "visits": [
        {
          "text": "Lac Zell (Zeller See), étendue d'eau de 4,5 km sur 1,5 km enchâssée entre le massif du Kitzsteinhorn (3 203 m) et la Schmittenhöhe (1 965 m). La promenade complète fait 11,3 km et 2h30 sur un sentier plat sans dénivelé. Les eaux turquoise atteignent 24°C en juillet-août.",
          "visit_duration_min": 120
        },
        {
          "text": "Ville de Zell am See, bourg médiéval fondé au VIIIe siècle par des moines. La tour romane de l'église Saint-Hippolyte (XIIe siècle) domine la vieille ville. Les ruelles du centre historique avec leurs boutiques et restaurants contrastent avec les panoramas alpins tout autour.",
          "visit_duration_min": 60
        },
        {
          "text": "Téléphérique de la Schmittenhöhe (1 965 m), montée en 15 minutes depuis le centre-ville. Au sommet, sentier panoramique Pinzgauer Spaziergang offrant des vues sur 30 sommets de plus de 3 000 m dont le Grossglockner. Restaurant d'altitude avec terrasse au soleil.",
          "visit_duration_min": 120
        }
      ],
      "activities": [
        {
          "text": "Route du Grossglockner (48 km, péage ~36 €), route panoramique à 36 virages numérotés traversant le Parc national des Hohe Tauern. Départ depuis Fusch an der Glocknerstraße. Arrêts obligatoires : Edelweißspitze (2 577 m, panorama 360°) et Kaiser-Franz-Josefs-Höhe (2 369 m) pour vue sur le glacier Pasterze."
        },
        {
          "text": "Baignade dans le lac Zell depuis la plage publique de Seespitz ou la plage du camping municipal. Pédalos, voile et paddle en location sur la rive ouest. Eau à 22-24°C en juillet-août."
        }
      ],
      "days_plan": [
        {
          "itin_id": "AT::eastern-alps::lacs-et-montagnes-7j",
          "itin_title": "Road Trip Autriche : Vienne, Salzbourg, Tyrol et Lacs Alpins",
          "day": 7
        },
        {
          "itin_id": "AT::autriche::two-weeks-explorers",
          "itin_title": "Autriche en trois semaines : Wachau, Alpes et Salzbourg",
          "day": 5
        }
      ],
      "rating": 7.7,
      "place_type": "medium_city",
      "suggested_days": 0.5
    },
    {
      "place_id": "AT::zillertal",
      "name": "Zillertal",
      "cc": "AT",
      "language": "fr",
      "coords": [
        47.2317,
        11.8715
      ],
      "lat": 47.2317,
      "lon": 11.8715,
      "visits": [
        {
          "text": "La vallée du Zillertal s'ouvre à l'est d'Innsbruck, encadrée par des sommets dépassant les 3 500 mètres. Ses villages - Zell am Ziller, Mayrhofen, Finkenberg - conservent leurs grandes maisons aux façades blanches et leurs clochers pointus. À Zell am Ziller, ne manquez pas la fromagerie Erlebnis-Sennerei Zillertal : une exposition interactive explique comment les fromages d'alpage sont fabriqués depuis des siècles.",
          "visit_duration_min": 60
        },
        {
          "text": "Alpbach, village voisin dans la vallée de l'Alpbachtal, a été élu plusieurs fois le plus beau village d'Autriche. Une loi locale interdit tout autre matériau de construction que le bois : résultat, une cohérence architecturale rare. Les balcons couverts de géraniums, les fontaines en pierre et les granges adossées aux maisons d'habitation composent un tableau de carte postale que les années n'ont pas altéré.",
          "visit_duration_min": 75
        },
        {
          "text": "Rattenberg, à l'entrée de la vallée, est la plus petite ville d'Autriche avec seulement 400 habitants. Réputée depuis le Moyen Âge pour son artisanat du verre, ses ruelles médiévales et son église augustinienne baroques méritent une pause. Les ateliers et boutiques de verre soufflé artisanal se succèdent dans la rue principale.",
          "visit_duration_min": 45
        }
      ],
      "activities": [
        {
          "text": "Randonnée familiale dans l'Alpbachtal sur les sentiers balisés qui partent du village d'Alpbach. Pour monter rapidement en altitude sans effort, les télécabines des Wiedersbergerhornbahn emmènent les familles jusqu'à des panoramas sur les Alpes de Zillertal et le lac d'Achensee. Depuis la station supérieure, une heure de marche suffit pour atteindre le sommet à 2 127 mètres."
        },
        {
          "text": "Embarquez dans le Zillertalbahn, train à vapeur historique qui relie Jenbach à Mayrhofen sur 32 km, franchissant 35 ponts au-dessus de la rivière Ziller. À 35 km/h maximum, les wagons en bois ouvrent sur les prairies et villages de la vallée. Les enfants adorent ce voyage dans une locomotive d'époque."
        }
      ],
      "days_plan": [
        {
          "itin_id": "AT::austria-family-roadtrip",
          "itin_title": "Voyage Autriche en Famille : Montagnes, Lacs et Palais Impériaux",
          "day": 2
        }
      ],
      "map_keywords": [
        "Mayrhofen Zillertal",
        "Zell am Ziller",
        "Zillertalbahn train à vapeur",
        "Alpbach village fleuri Tyrol",
        "Reither See Alpbachtal",
        "Rattenberg ville verrerie",
        "Gorges Tiefenbachklamm Kramsach"
      ],
      "rating": 7.1,
      "place_type": "nature",
      "suggested_days": 1.5
    }
  ]
}